{"assets":{"7ABF9014F850E57025F9AD2D5D453401":{"type":"texture","index":6,"assetRequest":{"type":"slide","state":"contents","slide":"878BBE58-D4EC-4BEF-AEB9-ACE275504A9E"},"url":{"web":"assets/878BBE58-D4EC-4BEF-AEB9-ACE275504A9E.svgmap"},"width":408,"height":32},"498E23C82CA78A4BCD7BA88E5243B6FC":{"type":"texture","index":0,"assetRequest":{"type":"slide","state":"contents","slide":"878BBE58-D4EC-4BEF-AEB9-ACE275504A9E"},"url":{"web":"assets/878BBE58-D4EC-4BEF-AEB9-ACE275504A9E.svgmap"},"width":1024,"height":768},"3B5F094C1248F300D48710F408F34F8C":{"type":"texture","index":7,"assetRequest":{"type":"slide","state":"contents","slide":"878BBE58-D4EC-4BEF-AEB9-ACE275504A9E"},"url":{"web":"assets/878BBE58-D4EC-4BEF-AEB9-ACE275504A9E.svgmap"},"width":932,"height":259},"9524C4C86A6D666694F5B7B992FC70D1":{"type":"texture","index":8,"assetRequest":{"type":"slide","state":"outgoing","slide":"878BBE58-D4EC-4BEF-AEB9-ACE275504A9E"},"url":{"web":"assets/878BBE58-D4EC-4BEF-AEB9-ACE275504A9E.svgmap"},"width":1024,"height":768},"149C513879A790C36DF1D69D3EE61D09":{"type":"texture","index":9,"assetRequest":{"type":"slide","state":"incoming","slide":"B83EA84B-CC63-46E1-9F2F-FC386B20C83D"},"url":{"web":"assets/878BBE58-D4EC-4BEF-AEB9-ACE275504A9E.svgmap"},"width":1024,"height":768},"4758254A91C6C40CDEF4C0480BD9C517":{"type":"texture","index":4,"assetRequest":{"type":"slide","state":"contents","slide":"878BBE58-D4EC-4BEF-AEB9-ACE275504A9E"},"url":{"web":"assets/878BBE58-D4EC-4BEF-AEB9-ACE275504A9E.svgmap"},"width":286,"height":38},"231BDE32EF29B8046E109B565B0FE118":{"type":"texture","index":5,"assetRequest":{"type":"slide","state":"contents","slide":"878BBE58-D4EC-4BEF-AEB9-ACE275504A9E"},"url":{"web":"assets/878BBE58-D4EC-4BEF-AEB9-ACE275504A9E.svgmap"},"width":126,"height":34},"962E02FEABF206A1B6439CEC08333644":{"type":"texture","index":2,"assetRequest":{"type":"slide","state":"contents","slide":"878BBE58-D4EC-4BEF-AEB9-ACE275504A9E"},"url":{"web":"assets/878BBE58-D4EC-4BEF-AEB9-ACE275504A9E.svgmap"},"width":191,"height":38},"75996AAD15AADBAD0B351AA53800C12A":{"type":"texture","index":1,"assetRequest":{"type":"slide","state":"contents","slide":"878BBE58-D4EC-4BEF-AEB9-ACE275504A9E"},"url":{"web":"assets/878BBE58-D4EC-4BEF-AEB9-ACE275504A9E.svgmap"},"width":584,"height":76},"B4C91EE1E5B54B1652C89239E55F6478":{"type":"texture","index":3,"assetRequest":{"type":"slide","state":"contents","slide":"878BBE58-D4EC-4BEF-AEB9-ACE275504A9E"},"url":{"web":"assets/878BBE58-D4EC-4BEF-AEB9-ACE275504A9E.svgmap"},"width":197,"height":32}},"events":[{"effects":[{"beginTime":0,"baseLayer":{"animations":[],"initialState":{"affineTransform":[1,0,0,1,0,0],"masksToBounds":false,"rotation":0,"scale":1,"position":{"pointX":512.0000114440918,"pointY":595.9263916015625},"width":464.3575668334961,"sublayerTransform":[1,0,0,0,0,1,0,0,0,0,1,0,0,0,0,1],"contentsRect":{"y":0,"x":0,"width":1,"height":1},"opacity":1,"edgeAntialiasingMask":251658240,"height":306.9999933242798,"hidden":false,"anchorPoint":{"pointX":0.5,"pointY":0.5}},"objectID":"ADA2DAAC-977A-43BE-A665-8069D27319AD","layers":[{"animations":[],"initialState":{"affineTransform":[1,0,0,1,0,0],"masksToBounds":false,"rotation":0,"scale":1,"position":{"pointX":232.1787719726562,"pointY":-58.42639493942261},"width":464.3575668334961,"sublayerTransform":[1,0,0,0,0,1,0,0,0,0,1,-0.0004922987690640373,0,0,0,1],"contentsRect":{"y":0,"x":0,"width":1,"height":1},"opacity":1,"edgeAntialiasingMask":251658240,"height":306.9999933242798,"hidden":false,"anchorPoint":{"pointX":0.499999975355001,"pointY":-0.1903139941690736}},"layers":[{"animations":[{"timeOffset":0,"from":{"scalar":true},"beginTime":1e-100,"repeatCount":0,"fillMode":"both","property":"hidden","autoreverses":false,"duration":0.01,"to":{"scalar":false}}],"layers":[],"texturedRectangle":{"singleTextureOpacity":1,"textXHeight":0.4964210526315789,"textBaseline":0.7406986512635884,"isBackgroundTexture":false,"isVerticalText":false,"textColor":[0,0,0,1],"textureType":6},"initialState":{"affineTransform":[1,0,0,1,0,0],"masksToBounds":false,"rotation":0,"scale":1,"position":{"pointX":133.6787719726562,"pointY":29.57360506057739},"width":191,"sublayerTransform":[1,0,0,0,0,1,0,0,0,0,1,0,0,0,0,1],"contentsRect":{"y":0,"x":0,"width":1,"height":1},"opacity":1,"edgeAntialiasingMask":0,"height":38,"hidden":true,"anchorPoint":{"pointX":0.5,"pointY":0.5}},"texture":"962E02FEABF206A1B6439CEC08333644"}]},{"animations":[],"layers":[],"texturedRectangle":{"singleTextureOpacity":1,"textXHeight":0.5894999999999999,"textBaseline":0.8795796483755112,"isBackgroundTexture":false,"isVerticalText":false,"textColor":[0,0,0,1],"textureType":6},"initialState":{"affineTransform":[1,0,0,1,0,0],"masksToBounds":false,"rotation":0,"scale":1,"position":{"pointX":136.6787719726562,"pointY":90.57360506057739},"width":197,"sublayerTransform":[1,0,0,0,0,1,0,0,0,0,1,0,0,0,0,1],"contentsRect":{"y":0,"x":0,"width":1,"height":1},"opacity":1,"edgeAntialiasingMask":0,"height":32,"hidden":true,"anchorPoint":{"pointX":0.5,"pointY":0.5}},"texture":"B4C91EE1E5B54B1652C89239E55F6478"},{"animations":[],"layers":[],"texturedRectangle":{"singleTextureOpacity":1,"textXHeight":0.4964210526315789,"textBaseline":0.7406986512635884,"isBackgroundTexture":false,"isVerticalText":false,"textColor":[0,0,0,1],"textureType":6},"initialState":{"affineTransform":[1,0,0,1,0,0],"masksToBounds":false,"rotation":0,"scale":1,"position":{"pointX":181.1787719726562,"pointY":157.5736050605774},"width":286,"sublayerTransform":[1,0,0,0,0,1,0,0,0,0,1,0,0,0,0,1],"contentsRect":{"y":0,"x":0,"width":1,"height":1},"opacity":1,"edgeAntialiasingMask":0,"height":38,"hidden":true,"anchorPoint":{"pointX":0.5,"pointY":0.5}},"texture":"4758254A91C6C40CDEF4C0480BD9C517"},{"animations":[],"layers":[],"texturedRectangle":{"singleTextureOpacity":1,"textXHeight":0.5548235294117646,"textBaseline":0.7101926102357752,"isBackgroundTexture":false,"isVerticalText":false,"textColor":[0,0,0,1],"textureType":6},"initialState":{"affineTransform":[1,0,0,1,0,0],"masksToBounds":false,"rotation":0,"scale":1,"position":{"pointX":101.1787719726562,"pointY":223.5736050605774},"width":126,"sublayerTransform":[1,0,0,0,0,1,0,0,0,0,1,0,0,0,0,1],"contentsRect":{"y":0,"x":0,"width":1,"height":1},"opacity":1,"edgeAntialiasingMask":0,"height":34,"hidden":true,"anchorPoint":{"pointX":0.5,"pointY":0.5}},"texture":"231BDE32EF29B8046E109B565B0FE118"},{"animations":[],"layers":[],"texturedRectangle":{"singleTextureOpacity":1,"textXHeight":0.5894999999999999,"textBaseline":0.8795796483755112,"isBackgroundTexture":false,"isVerticalText":false,"textColor":[0,0,0,1],"textureType":6},"initialState":{"affineTransform":[1,0,0,1,0,0],"masksToBounds":false,"rotation":0,"scale":1,"position":{"pointX":242.1787719726562,"pointY":282.5736050605774},"width":408,"sublayerTransform":[1,0,0,0,0,1,0,0,0,0,1,0,0,0,0,1],"contentsRect":{"y":0,"x":0,"width":1,"height":1},"opacity":1,"edgeAntialiasingMask":0,"height":32,"hidden":true,"anchorPoint":{"pointX":0.5,"pointY":0.5}},"texture":"7ABF9014F850E57025F9AD2D5D453401"}]},"effects":[],"duration":0.01,"type":"buildIn","name":"apple:appear","objectID":"ADA2DAAC-977A-43BE-A665-8069D27319AD"}],"automaticPlay":false,"hyperlinks":[],"accessibility":[{"text":"Property Access","targetRectangle":{"y":72,"x":216.36,"width":591.2800000000002,"height":96}},{"text":" function load(obj) {","targetRectangle":{"y":191.9975843429565,"x":60.09092712402344,"width":869.4,"height":77}},{"text":"   return obj.x;","targetRectangle":{"y":268.9975843429565,"x":60.09092712402344,"width":662.4,"height":77}},{"text":" }","targetRectangle":{"y":345.9975843429565,"x":60.09092712402344,"width":82.80000000000001,"height":77}}],"baseLayer":{"animations":[],"initialState":{"affineTransform":[1,0,0,1,0,0],"masksToBounds":false,"rotation":0,"scale":1,"position":{"pointX":512,"pointY":384},"width":1024,"sublayerTransform":[1,0,0,0,0,1,0,0,0,0,1,0,0,0,0,1],"contentsRect":{"y":0,"x":0,"width":1,"height":1},"opacity":1,"edgeAntialiasingMask":251658240,"height":768,"hidden":false,"anchorPoint":{"pointX":0.5,"pointY":0.5}},"layers":[{"animations":[],"initialState":{"affineTransform":[1,0,0,1,0,0],"masksToBounds":false,"rotation":0,"scale":1,"position":{"pointX":512,"pointY":384},"width":1024,"sublayerTransform":[1,0,0,0,0,1,0,0,0,0,1,0,0,0,0,1],"contentsRect":{"y":0,"x":0,"width":1,"height":1},"opacity":1,"edgeAntialiasingMask":251658240,"height":768,"hidden":false,"anchorPoint":{"pointX":0.5,"pointY":0.5}},"layers":[{"animations":[],"initialState":{"affineTransform":[1,0,0,1,0,0],"masksToBounds":false,"rotation":0,"scale":1,"position":{"pointX":512,"pointY":384},"width":1024,"sublayerTransform":[1,0,0,0,0,1,0,0,0,0,1,0,0,0,0,1],"contentsRect":{"y":0,"x":0,"width":1,"height":1},"opacity":1,"edgeAntialiasingMask":251658240,"height":768,"hidden":false,"anchorPoint":{"pointX":0.5,"pointY":0.5}},"layers":[{"animations":[],"layers":[],"texturedRectangle":{"isBackgroundTexture":true,"singleTextureOpacity":1,"textureType":1,"textBaseline":0,"textXHeight":0,"isVerticalText":false},"initialState":{"affineTransform":[1,0,0,1,0,0],"masksToBounds":false,"rotation":0,"scale":1,"position":{"pointX":512,"pointY":384},"width":1024,"sublayerTransform":[1,0,0,0,0,1,0,0,0,0,1,0,0,0,0,1],"contentsRect":{"y":0,"x":0,"width":1,"height":1},"opacity":1,"edgeAntialiasingMask":0,"height":768,"hidden":false,"anchorPoint":{"pointX":0.5,"pointY":0.5}},"texture":"498E23C82CA78A4BCD7BA88E5243B6FC"}]}]},{"animations":[],"initialState":{"affineTransform":[1,0,0,1,0,0],"masksToBounds":false,"rotation":0,"scale":1,"position":{"pointX":512,"pointY":384},"width":1024,"sublayerTransform":[1,0,0,0,0,1,0,0,0,0,1,0,0,0,0,1],"contentsRect":{"y":0,"x":0,"width":1,"height":1},"opacity":1,"edgeAntialiasingMask":251658240,"height":768,"hidden":false,"anchorPoint":{"pointX":0.5,"pointY":0.5}},"layers":[{"animations":[],"initialState":{"affineTransform":[1,0,0,1,0,0],"masksToBounds":false,"rotation":0,"scale":1,"position":{"pointX":512,"pointY":120},"width":874,"sublayerTransform":[1,0,0,0,0,1,0,0,0,0,1,0,0,0,0,1],"contentsRect":{"y":0,"x":0,"width":1,"height":1},"opacity":1,"edgeAntialiasingMask":251658240,"height":170,"hidden":false,"anchorPoint":{"pointX":0.5,"pointY":0.5}},"objectID":"441ADC2F-0FBE-4955-BB1E-81EEA0F1C91D","layers":[{"animations":[],"layers":[],"texturedRectangle":{"singleTextureOpacity":1,"textXHeight":0.5515789473684211,"textBaseline":0.77105712890625,"isBackgroundTexture":true,"isVerticalText":false,"textColor":[0,0,0,1],"textureType":6},"initialState":{"affineTransform":[1,0,0,1,0,0],"masksToBounds":false,"rotation":0,"scale":1,"position":{"pointX":438,"pointY":94},"width":584,"sublayerTransform":[1,0,0,0,0,1,0,0,0,0,1,0,0,0,0,1],"contentsRect":{"y":0,"x":0,"width":1,"height":1},"opacity":1,"edgeAntialiasingMask":0,"height":76,"hidden":false,"anchorPoint":{"pointX":0.5,"pointY":0.5}},"texture":"75996AAD15AADBAD0B351AA53800C12A"}]}]},{"animations":[],"initialState":{"affineTransform":[1,0,0,1,0,0],"masksToBounds":false,"rotation":0,"scale":1,"position":{"pointX":512,"pointY":384},"width":1024,"sublayerTransform":[1,0,0,0,0,1,0,0,0,0,1,0,0,0,0,1],"contentsRect":{"y":0,"x":0,"width":1,"height":1},"opacity":1,"edgeAntialiasingMask":251658240,"height":768,"hidden":false,"anchorPoint":{"pointX":0.5,"pointY":0.5}},"layers":[{"animations":[],"initialState":{"affineTransform":[1,0,0,1,0,0],"masksToBounds":false,"rotation":0,"scale":1,"position":{"pointX":512.0000114440918,"pointY":595.9263916015625},"width":464.3575668334961,"sublayerTransform":[1,0,0,0,0,1,0,0,0,0,1,0,0,0,0,1],"contentsRect":{"y":0,"x":0,"width":1,"height":1},"opacity":1,"edgeAntialiasingMask":251658240,"height":306.9999933242798,"hidden":false,"anchorPoint":{"pointX":0.5,"pointY":0.5}},"objectID":"ADA2DAAC-977A-43BE-A665-8069D27319AD","layers":[{"animations":[],"layers":[],"texturedRectangle":{"singleTextureOpacity":1,"textXHeight":0.4964210526315789,"textBaseline":0.7406986512635884,"isBackgroundTexture":false,"isVerticalText":false,"textColor":[0,0,0,1],"textureType":6},"initialState":{"affineTransform":[1,0,0,1,0,0],"masksToBounds":false,"rotation":0,"scale":1,"position":{"pointX":133.6787719726562,"pointY":29.57360506057739},"width":191,"sublayerTransform":[1,0,0,0,0,1,0,0,0,0,1,0,0,0,0,1],"contentsRect":{"y":0,"x":0,"width":1,"height":1},"opacity":1,"edgeAntialiasingMask":0,"height":38,"hidden":true,"anchorPoint":{"pointX":0.5,"pointY":0.5}},"texture":"962E02FEABF206A1B6439CEC08333644"},{"animations":[],"layers":[],"texturedRectangle":{"singleTextureOpacity":1,"textXHeight":0.5894999999999999,"textBaseline":0.8795796483755112,"isBackgroundTexture":false,"isVerticalText":false,"textColor":[0,0,0,1],"textureType":6},"initialState":{"affineTransform":[1,0,0,1,0,0],"masksToBounds":false,"rotation":0,"scale":1,"position":{"pointX":136.6787719726562,"pointY":90.57360506057739},"width":197,"sublayerTransform":[1,0,0,0,0,1,0,0,0,0,1,0,0,0,0,1],"contentsRect":{"y":0,"x":0,"width":1,"height":1},"opacity":1,"edgeAntialiasingMask":0,"height":32,"hidden":true,"anchorPoint":{"pointX":0.5,"pointY":0.5}},"texture":"B4C91EE1E5B54B1652C89239E55F6478"},{"animations":[],"layers":[],"texturedRectangle":{"singleTextureOpacity":1,"textXHeight":0.4964210526315789,"textBaseline":0.7406986512635884,"isBackgroundTexture":false,"isVerticalText":false,"textColor":[0,0,0,1],"textureType":6},"initialState":{"affineTransform":[1,0,0,1,0,0],"masksToBounds":false,"rotation":0,"scale":1,"position":{"pointX":181.1787719726562,"pointY":157.5736050605774},"width":286,"sublayerTransform":[1,0,0,0,0,1,0,0,0,0,1,0,0,0,0,1],"contentsRect":{"y":0,"x":0,"width":1,"height":1},"opacity":1,"edgeAntialiasingMask":0,"height":38,"hidden":true,"anchorPoint":{"pointX":0.5,"pointY":0.5}},"texture":"4758254A91C6C40CDEF4C0480BD9C517"},{"animations":[],"layers":[],"texturedRectangle":{"singleTextureOpacity":1,"textXHeight":0.5548235294117646,"textBaseline":0.7101926102357752,"isBackgroundTexture":false,"isVerticalText":false,"textColor":[0,0,0,1],"textureType":6},"initialState":{"affineTransform":[1,0,0,1,0,0],"masksToBounds":false,"rotation":0,"scale":1,"position":{"pointX":101.1787719726562,"pointY":223.5736050605774},"width":126,"sublayerTransform":[1,0,0,0,0,1,0,0,0,0,1,0,0,0,0,1],"contentsRect":{"y":0,"x":0,"width":1,"height":1},"opacity":1,"edgeAntialiasingMask":0,"height":34,"hidden":true,"anchorPoint":{"pointX":0.5,"pointY":0.5}},"texture":"231BDE32EF29B8046E109B565B0FE118"},{"animations":[],"layers":[],"texturedRectangle":{"singleTextureOpacity":1,"textXHeight":0.5894999999999999,"textBaseline":0.8795796483755112,"isBackgroundTexture":false,"isVerticalText":false,"textColor":[0,0,0,1],"textureType":6},"initialState":{"affineTransform":[1,0,0,1,0,0],"masksToBounds":false,"rotation":0,"scale":1,"position":{"pointX":242.1787719726562,"pointY":282.5736050605774},"width":408,"sublayerTransform":[1,0,0,0,0,1,0,0,0,0,1,0,0,0,0,1],"contentsRect":{"y":0,"x":0,"width":1,"height":1},"opacity":1,"edgeAntialiasingMask":0,"height":32,"hidden":true,"anchorPoint":{"pointX":0.5,"pointY":0.5}},"texture":"7ABF9014F850E57025F9AD2D5D453401"}]}]},{"animations":[],"initialState":{"affineTransform":[1,0,0,1,0,0],"masksToBounds":false,"rotation":0,"scale":1,"position":{"pointX":512,"pointY":384},"width":1024,"sublayerTransform":[1,0,0,0,0,1,0,0,0,0,1,0,0,0,0,1],"contentsRect":{"y":0,"x":0,"width":1,"height":1},"opacity":1,"edgeAntialiasingMask":251658240,"height":768,"hidden":false,"anchorPoint":{"pointX":0.5,"pointY":0.5}},"layers":[{"animations":[],"initialState":{"affineTransform":[1,0,0,1,0,0],"masksToBounds":false,"rotation":0,"scale":1,"position":{"pointX":512,"pointY":307.4975891113281},"width":913.8181457519531,"sublayerTransform":[1,0,0,0,0,1,0,0,0,0,1,0,0,0,0,1],"contentsRect":{"y":0,"x":0,"width":1,"height":1},"opacity":1,"edgeAntialiasingMask":251658240,"height":241.0000095367432,"hidden":false,"anchorPoint":{"pointX":0.5,"pointY":0.5}},"objectID":"AFE8CA3E-FAF9-4767-B23E-13DFA2880110","layers":[{"animations":[],"layers":[],"texturedRectangle":{"singleTextureOpacity":1,"textXHeight":0,"shapePath":{"lineWidth":1,"flatness":0.6,"lineCapStyle":0,"elements":[{"type":"MoveToPoint","points":[[9.590927124023438,9.497584342956543]]},{"type":"AddLine","points":[[922.4090728759766,9.497584342956543]]},{"type":"AddLine","points":[[922.4090728759766,249.4975938796997]]},{"type":"AddLine","points":[[9.590927124023438,249.4975938796997]]},{"type":"CloseSubpath"},{"type":"MoveToPoint","points":[[9.590927124023438,9.497584342956543]]}],"windingRule":0,"lineJoinStyle":0,"miterLimit":10},"isBackgroundTexture":true,"textBaseline":0,"isVerticalText":false,"textureType":5},"initialState":{"affineTransform":[1,0,0,1,0,0],"masksToBounds":false,"rotation":0,"scale":1,"position":{"pointX":456.9090728759766,"pointY":120.5024156570435},"width":932,"sublayerTransform":[1,0,0,0,0,1,0,0,0,0,1,0,0,0,0,1],"contentsRect":{"y":0,"x":0,"width":1,"height":1},"opacity":1,"edgeAntialiasingMask":0,"height":259,"hidden":false,"anchorPoint":{"pointX":0.5,"pointY":0.5}},"texture":"3B5F094C1248F300D48710F408F34F8C"}]}]}]}},{"effects":[{"beginTime":0,"baseLayer":{"animations":[],"initialState":{"affineTransform":[1,0,0,1,0,0],"masksToBounds":false,"rotation":0,"scale":1,"position":{"pointX":512.0000114440918,"pointY":595.9263916015625},"width":464.3575668334961,"sublayerTransform":[1,0,0,0,0,1,0,0,0,0,1,0,0,0,0,1],"contentsRect":{"y":0,"x":0,"width":1,"height":1},"opacity":1,"edgeAntialiasingMask":251658240,"height":306.9999933242798,"hidden":false,"anchorPoint":{"pointX":0.5,"pointY":0.5}},"objectID":"ADA2DAAC-977A-43BE-A665-8069D27319AD","layers":[{"animations":[],"layers":[],"texturedRectangle":{"singleTextureOpacity":1,"textXHeight":0.4964210526315789,"textBaseline":0.7406986512635884,"isBackgroundTexture":false,"isVerticalText":false,"textColor":[0,0,0,1],"textureType":6},"initialState":{"affineTransform":[1,0,0,1,0,0],"masksToBounds":false,"rotation":0,"scale":1,"position":{"pointX":133.6787719726562,"pointY":29.57360506057739},"width":191,"sublayerTransform":[1,0,0,0,0,1,0,0,0,0,1,0,0,0,0,1],"contentsRect":{"y":0,"x":0,"width":1,"height":1},"opacity":1,"edgeAntialiasingMask":0,"height":38,"hidden":false,"anchorPoint":{"pointX":0.5,"pointY":0.5}},"texture":"962E02FEABF206A1B6439CEC08333644"},{"animations":[],"initialState":{"affineTransform":[1,0,0,1,0,0],"masksToBounds":false,"rotation":0,"scale":1,"position":{"pointX":232.1787719726562,"pointY":-58.42639493942261},"width":464.3575668334961,"sublayerTransform":[1,0,0,0,0,1,0,0,0,0,1,-0.0004922987690640373,0,0,0,1],"contentsRect":{"y":0,"x":0,"width":1,"height":1},"opacity":1,"edgeAntialiasingMask":251658240,"height":306.9999933242798,"hidden":false,"anchorPoint":{"pointX":0.499999975355001,"pointY":-0.1903139941690736}},"layers":[{"animations":[{"timeOffset":0,"from":{"scalar":true},"beginTime":1e-100,"repeatCount":0,"fillMode":"both","property":"hidden","autoreverses":false,"duration":0.01,"to":{"scalar":false}}],"layers":[],"texturedRectangle":{"singleTextureOpacity":1,"textXHeight":0.5894999999999999,"textBaseline":0.8795796483755112,"isBackgroundTexture":false,"isVerticalText":false,"textColor":[0,0,0,1],"textureType":6},"initialState":{"affineTransform":[1,0,0,1,0,0],"masksToBounds":false,"rotation":0,"scale":1,"position":{"pointX":136.6787719726562,"pointY":90.57360506057739},"width":197,"sublayerTransform":[1,0,0,0,0,1,0,0,0,0,1,0,0,0,0,1],"contentsRect":{"y":0,"x":0,"width":1,"height":1},"opacity":1,"edgeAntialiasingMask":0,"height":32,"hidden":true,"anchorPoint":{"pointX":0.5,"pointY":0.5}},"texture":"B4C91EE1E5B54B1652C89239E55F6478"}]},{"animations":[],"layers":[],"texturedRectangle":{"singleTextureOpacity":1,"textXHeight":0.4964210526315789,"textBaseline":0.7406986512635884,"isBackgroundTexture":false,"isVerticalText":false,"textColor":[0,0,0,1],"textureType":6},"initialState":{"affineTransform":[1,0,0,1,0,0],"masksToBounds":false,"rotation":0,"scale":1,"position":{"pointX":181.1787719726562,"pointY":157.5736050605774},"width":286,"sublayerTransform":[1,0,0,0,0,1,0,0,0,0,1,0,0,0,0,1],"contentsRect":{"y":0,"x":0,"width":1,"height":1},"opacity":1,"edgeAntialiasingMask":0,"height":38,"hidden":true,"anchorPoint":{"pointX":0.5,"pointY":0.5}},"texture":"4758254A91C6C40CDEF4C0480BD9C517"},{"animations":[],"layers":[],"texturedRectangle":{"singleTextureOpacity":1,"textXHeight":0.5548235294117646,"textBaseline":0.7101926102357752,"isBackgroundTexture":false,"isVerticalText":false,"textColor":[0,0,0,1],"textureType":6},"initialState":{"affineTransform":[1,0,0,1,0,0],"masksToBounds":false,"rotation":0,"scale":1,"position":{"pointX":101.1787719726562,"pointY":223.5736050605774},"width":126,"sublayerTransform":[1,0,0,0,0,1,0,0,0,0,1,0,0,0,0,1],"contentsRect":{"y":0,"x":0,"width":1,"height":1},"opacity":1,"edgeAntialiasingMask":0,"height":34,"hidden":true,"anchorPoint":{"pointX":0.5,"pointY":0.5}},"texture":"231BDE32EF29B8046E109B565B0FE118"},{"animations":[],"layers":[],"texturedRectangle":{"singleTextureOpacity":1,"textXHeight":0.5894999999999999,"textBaseline":0.8795796483755112,"isBackgroundTexture":false,"isVerticalText":false,"textColor":[0,0,0,1],"textureType":6},"initialState":{"affineTransform":[1,0,0,1,0,0],"masksToBounds":false,"rotation":0,"scale":1,"position":{"pointX":242.1787719726562,"pointY":282.5736050605774},"width":408,"sublayerTransform":[1,0,0,0,0,1,0,0,0,0,1,0,0,0,0,1],"contentsRect":{"y":0,"x":0,"width":1,"height":1},"opacity":1,"edgeAntialiasingMask":0,"height":32,"hidden":true,"anchorPoint":{"pointX":0.5,"pointY":0.5}},"texture":"7ABF9014F850E57025F9AD2D5D453401"}]},"effects":[],"duration":0.01,"type":"buildIn","name":"apple:appear","objectID":"ADA2DAAC-977A-43BE-A665-8069D27319AD"}],"automaticPlay":false,"hyperlinks":[],"accessibility":[{"text":"Property Access","targetRectangle":{"y":72,"x":216.36,"width":591.2800000000002,"height":96}},{"text":"TypeError","targetRectangle":{"y":446.4263949394226,"x":353.8212275505066,"width":154.332,"height":43}},{"text":" function load(obj) {","targetRectangle":{"y":191.9975843429565,"x":60.09092712402344,"width":869.4,"height":77}},{"text":"   return obj.x;","targetRectangle":{"y":268.9975843429565,"x":60.09092712402344,"width":662.4,"height":77}},{"text":" }","targetRectangle":{"y":345.9975843429565,"x":60.09092712402344,"width":82.80000000000001,"height":77}}],"baseLayer":{"animations":[],"initialState":{"affineTransform":[1,0,0,1,0,0],"masksToBounds":false,"rotation":0,"scale":1,"position":{"pointX":512,"pointY":384},"width":1024,"sublayerTransform":[1,0,0,0,0,1,0,0,0,0,1,0,0,0,0,1],"contentsRect":{"y":0,"x":0,"width":1,"height":1},"opacity":1,"edgeAntialiasingMask":251658240,"height":768,"hidden":false,"anchorPoint":{"pointX":0.5,"pointY":0.5}},"layers":[{"animations":[],"initialState":{"affineTransform":[1,0,0,1,0,0],"masksToBounds":false,"rotation":0,"scale":1,"position":{"pointX":512,"pointY":384},"width":1024,"sublayerTransform":[1,0,0,0,0,1,0,0,0,0,1,0,0,0,0,1],"contentsRect":{"y":0,"x":0,"width":1,"height":1},"opacity":1,"edgeAntialiasingMask":251658240,"height":768,"hidden":false,"anchorPoint":{"pointX":0.5,"pointY":0.5}},"layers":[{"animations":[],"initialState":{"affineTransform":[1,0,0,1,0,0],"masksToBounds":false,"rotation":0,"scale":1,"position":{"pointX":512,"pointY":384},"width":1024,"sublayerTransform":[1,0,0,0,0,1,0,0,0,0,1,0,0,0,0,1],"contentsRect":{"y":0,"x":0,"width":1,"height":1},"opacity":1,"edgeAntialiasingMask":251658240,"height":768,"hidden":false,"anchorPoint":{"pointX":0.5,"pointY":0.5}},"layers":[{"animations":[],"layers":[],"texturedRectangle":{"isBackgroundTexture":true,"singleTextureOpacity":1,"textureType":1,"textBaseline":0,"textXHeight":0,"isVerticalText":false},"initialState":{"affineTransform":[1,0,0,1,0,0],"masksToBounds":false,"rotation":0,"scale":1,"position":{"pointX":512,"pointY":384},"width":1024,"sublayerTransform":[1,0,0,0,0,1,0,0,0,0,1,0,0,0,0,1],"contentsRect":{"y":0,"x":0,"width":1,"height":1},"opacity":1,"edgeAntialiasingMask":0,"height":768,"hidden":false,"anchorPoint":{"pointX":0.5,"pointY":0.5}},"texture":"498E23C82CA78A4BCD7BA88E5243B6FC"}]}]},{"animations":[],"initialState":{"affineTransform":[1,0,0,1,0,0],"masksToBounds":false,"rotation":0,"scale":1,"position":{"pointX":512,"pointY":384},"width":1024,"sublayerTransform":[1,0,0,0,0,1,0,0,0,0,1,0,0,0,0,1],"contentsRect":{"y":0,"x":0,"width":1,"height":1},"opacity":1,"edgeAntialiasingMask":251658240,"height":768,"hidden":false,"anchorPoint":{"pointX":0.5,"pointY":0.5}},"layers":[{"animations":[],"initialState":{"affineTransform":[1,0,0,1,0,0],"masksToBounds":false,"rotation":0,"scale":1,"position":{"pointX":512,"pointY":120},"width":874,"sublayerTransform":[1,0,0,0,0,1,0,0,0,0,1,0,0,0,0,1],"contentsRect":{"y":0,"x":0,"width":1,"height":1},"opacity":1,"edgeAntialiasingMask":251658240,"height":170,"hidden":false,"anchorPoint":{"pointX":0.5,"pointY":0.5}},"objectID":"441ADC2F-0FBE-4955-BB1E-81EEA0F1C91D","layers":[{"animations":[],"layers":[],"texturedRectangle":{"singleTextureOpacity":1,"textXHeight":0.5515789473684211,"textBaseline":0.77105712890625,"isBackgroundTexture":true,"isVerticalText":false,"textColor":[0,0,0,1],"textureType":6},"initialState":{"affineTransform":[1,0,0,1,0,0],"masksToBounds":false,"rotation":0,"scale":1,"position":{"pointX":438,"pointY":94},"width":584,"sublayerTransform":[1,0,0,0,0,1,0,0,0,0,1,0,0,0,0,1],"contentsRect":{"y":0,"x":0,"width":1,"height":1},"opacity":1,"edgeAntialiasingMask":0,"height":76,"hidden":false,"anchorPoint":{"pointX":0.5,"pointY":0.5}},"texture":"75996AAD15AADBAD0B351AA53800C12A"}]}]},{"animations":[],"initialState":{"affineTransform":[1,0,0,1,0,0],"masksToBounds":false,"rotation":0,"scale":1,"position":{"pointX":512,"pointY":384},"width":1024,"sublayerTransform":[1,0,0,0,0,1,0,0,0,0,1,0,0,0,0,1],"contentsRect":{"y":0,"x":0,"width":1,"height":1},"opacity":1,"edgeAntialiasingMask":251658240,"height":768,"hidden":false,"anchorPoint":{"pointX":0.5,"pointY":0.5}},"layers":[{"animations":[],"initialState":{"affineTransform":[1,0,0,1,0,0],"masksToBounds":false,"rotation":0,"scale":1,"position":{"pointX":512.0000114440918,"pointY":595.9263916015625},"width":464.3575668334961,"sublayerTransform":[1,0,0,0,0,1,0,0,0,0,1,0,0,0,0,1],"contentsRect":{"y":0,"x":0,"width":1,"height":1},"opacity":1,"edgeAntialiasingMask":251658240,"height":306.9999933242798,"hidden":false,"anchorPoint":{"pointX":0.5,"pointY":0.5}},"objectID":"ADA2DAAC-977A-43BE-A665-8069D27319AD","layers":[{"animations":[],"layers":[],"texturedRectangle":{"singleTextureOpacity":1,"textXHeight":0.4964210526315789,"textBaseline":0.7406986512635884,"isBackgroundTexture":false,"isVerticalText":false,"textColor":[0,0,0,1],"textureType":6},"initialState":{"affineTransform":[1,0,0,1,0,0],"masksToBounds":false,"rotation":0,"scale":1,"position":{"pointX":133.6787719726562,"pointY":29.57360506057739},"width":191,"sublayerTransform":[1,0,0,0,0,1,0,0,0,0,1,0,0,0,0,1],"contentsRect":{"y":0,"x":0,"width":1,"height":1},"opacity":1,"edgeAntialiasingMask":0,"height":38,"hidden":false,"anchorPoint":{"pointX":0.5,"pointY":0.5}},"texture":"962E02FEABF206A1B6439CEC08333644"},{"animations":[],"layers":[],"texturedRectangle":{"singleTextureOpacity":1,"textXHeight":0.5894999999999999,"textBaseline":0.8795796483755112,"isBackgroundTexture":false,"isVerticalText":false,"textColor":[0,0,0,1],"textureType":6},"initialState":{"affineTransform":[1,0,0,1,0,0],"masksToBounds":false,"rotation":0,"scale":1,"position":{"pointX":136.6787719726562,"pointY":90.57360506057739},"width":197,"sublayerTransform":[1,0,0,0,0,1,0,0,0,0,1,0,0,0,0,1],"contentsRect":{"y":0,"x":0,"width":1,"height":1},"opacity":1,"edgeAntialiasingMask":0,"height":32,"hidden":true,"anchorPoint":{"pointX":0.5,"pointY":0.5}},"texture":"B4C91EE1E5B54B1652C89239E55F6478"},{"animations":[],"layers":[],"texturedRectangle":{"singleTextureOpacity":1,"textXHeight":0.4964210526315789,"textBaseline":0.7406986512635884,"isBackgroundTexture":false,"isVerticalText":false,"textColor":[0,0,0,1],"textureType":6},"initialState":{"affineTransform":[1,0,0,1,0,0],"masksToBounds":false,"rotation":0,"scale":1,"position":{"pointX":181.1787719726562,"pointY":157.5736050605774},"width":286,"sublayerTransform":[1,0,0,0,0,1,0,0,0,0,1,0,0,0,0,1],"contentsRect":{"y":0,"x":0,"width":1,"height":1},"opacity":1,"edgeAntialiasingMask":0,"height":38,"hidden":true,"anchorPoint":{"pointX":0.5,"pointY":0.5}},"texture":"4758254A91C6C40CDEF4C0480BD9C517"},{"animations":[],"layers":[],"texturedRectangle":{"singleTextureOpacity":1,"textXHeight":0.5548235294117646,"textBaseline":0.7101926102357752,"isBackgroundTexture":false,"isVerticalText":false,"textColor":[0,0,0,1],"textureType":6},"initialState":{"affineTransform":[1,0,0,1,0,0],"masksToBounds":false,"rotation":0,"scale":1,"position":{"pointX":101.1787719726562,"pointY":223.5736050605774},"width":126,"sublayerTransform":[1,0,0,0,0,1,0,0,0,0,1,0,0,0,0,1],"contentsRect":{"y":0,"x":0,"width":1,"height":1},"opacity":1,"edgeAntialiasingMask":0,"height":34,"hidden":true,"anchorPoint":{"pointX":0.5,"pointY":0.5}},"texture":"231BDE32EF29B8046E109B565B0FE118"},{"animations":[],"layers":[],"texturedRectangle":{"singleTextureOpacity":1,"textXHeight":0.5894999999999999,"textBaseline":0.8795796483755112,"isBackgroundTexture":false,"isVerticalText":false,"textColor":[0,0,0,1],"textureType":6},"initialState":{"affineTransform":[1,0,0,1,0,0],"masksToBounds":false,"rotation":0,"scale":1,"position":{"pointX":242.1787719726562,"pointY":282.5736050605774},"width":408,"sublayerTransform":[1,0,0,0,0,1,0,0,0,0,1,0,0,0,0,1],"contentsRect":{"y":0,"x":0,"width":1,"height":1},"opacity":1,"edgeAntialiasingMask":0,"height":32,"hidden":true,"anchorPoint":{"pointX":0.5,"pointY":0.5}},"texture":"7ABF9014F850E57025F9AD2D5D453401"}]}]},{"animations":[],"initialState":{"affineTransform":[1,0,0,1,0,0],"masksToBounds":false,"rotation":0,"scale":1,"position":{"pointX":512,"pointY":384},"width":1024,"sublayerTransform":[1,0,0,0,0,1,0,0,0,0,1,0,0,0,0,1],"contentsRect":{"y":0,"x":0,"width":1,"height":1},"opacity":1,"edgeAntialiasingMask":251658240,"height":768,"hidden":false,"anchorPoint":{"pointX":0.5,"pointY":0.5}},"layers":[{"animations":[],"initialState":{"affineTransform":[1,0,0,1,0,0],"masksToBounds":false,"rotation":0,"scale":1,"position":{"pointX":512,"pointY":307.4975891113281},"width":913.8181457519531,"sublayerTransform":[1,0,0,0,0,1,0,0,0,0,1,0,0,0,0,1],"contentsRect":{"y":0,"x":0,"width":1,"height":1},"opacity":1,"edgeAntialiasingMask":251658240,"height":241.0000095367432,"hidden":false,"anchorPoint":{"pointX":0.5,"pointY":0.5}},"objectID":"AFE8CA3E-FAF9-4767-B23E-13DFA2880110","layers":[{"animations":[],"layers":[],"texturedRectangle":{"singleTextureOpacity":1,"textXHeight":0,"shapePath":{"lineWidth":1,"flatness":0.6,"lineCapStyle":0,"elements":[{"type":"MoveToPoint","points":[[9.590927124023438,9.497584342956543]]},{"type":"AddLine","points":[[922.4090728759766,9.497584342956543]]},{"type":"AddLine","points":[[922.4090728759766,249.4975938796997]]},{"type":"AddLine","points":[[9.590927124023438,249.4975938796997]]},{"type":"CloseSubpath"},{"type":"MoveToPoint","points":[[9.590927124023438,9.497584342956543]]}],"windingRule":0,"lineJoinStyle":0,"miterLimit":10},"isBackgroundTexture":true,"textBaseline":0,"isVerticalText":false,"textureType":5},"initialState":{"affineTransform":[1,0,0,1,0,0],"masksToBounds":false,"rotation":0,"scale":1,"position":{"pointX":456.9090728759766,"pointY":120.5024156570435},"width":932,"sublayerTransform":[1,0,0,0,0,1,0,0,0,0,1,0,0,0,0,1],"contentsRect":{"y":0,"x":0,"width":1,"height":1},"opacity":1,"edgeAntialiasingMask":0,"height":259,"hidden":false,"anchorPoint":{"pointX":0.5,"pointY":0.5}},"texture":"3B5F094C1248F300D48710F408F34F8C"}]}]}]}},{"effects":[{"beginTime":0,"baseLayer":{"animations":[],"initialState":{"affineTransform":[1,0,0,1,0,0],"masksToBounds":false,"rotation":0,"scale":1,"position":{"pointX":512.0000114440918,"pointY":595.9263916015625},"width":464.3575668334961,"sublayerTransform":[1,0,0,0,0,1,0,0,0,0,1,0,0,0,0,1],"contentsRect":{"y":0,"x":0,"width":1,"height":1},"opacity":1,"edgeAntialiasingMask":251658240,"height":306.9999933242798,"hidden":false,"anchorPoint":{"pointX":0.5,"pointY":0.5}},"objectID":"ADA2DAAC-977A-43BE-A665-8069D27319AD","layers":[{"animations":[],"layers":[],"texturedRectangle":{"singleTextureOpacity":1,"textXHeight":0.4964210526315789,"textBaseline":0.7406986512635884,"isBackgroundTexture":false,"isVerticalText":false,"textColor":[0,0,0,1],"textureType":6},"initialState":{"affineTransform":[1,0,0,1,0,0],"masksToBounds":false,"rotation":0,"scale":1,"position":{"pointX":133.6787719726562,"pointY":29.57360506057739},"width":191,"sublayerTransform":[1,0,0,0,0,1,0,0,0,0,1,0,0,0,0,1],"contentsRect":{"y":0,"x":0,"width":1,"height":1},"opacity":1,"edgeAntialiasingMask":0,"height":38,"hidden":false,"anchorPoint":{"pointX":0.5,"pointY":0.5}},"texture":"962E02FEABF206A1B6439CEC08333644"},{"animations":[],"layers":[],"texturedRectangle":{"singleTextureOpacity":1,"textXHeight":0.5894999999999999,"textBaseline":0.8795796483755112,"isBackgroundTexture":false,"isVerticalText":false,"textColor":[0,0,0,1],"textureType":6},"initialState":{"affineTransform":[1,0,0,1,0,0],"masksToBounds":false,"rotation":0,"scale":1,"position":{"pointX":136.6787719726562,"pointY":90.57360506057739},"width":197,"sublayerTransform":[1,0,0,0,0,1,0,0,0,0,1,0,0,0,0,1],"contentsRect":{"y":0,"x":0,"width":1,"height":1},"opacity":1,"edgeAntialiasingMask":0,"height":32,"hidden":false,"anchorPoint":{"pointX":0.5,"pointY":0.5}},"texture":"B4C91EE1E5B54B1652C89239E55F6478"},{"animations":[],"initialState":{"affineTransform":[1,0,0,1,0,0],"masksToBounds":false,"rotation":0,"scale":1,"position":{"pointX":232.1787719726562,"pointY":-58.42639493942261},"width":464.3575668334961,"sublayerTransform":[1,0,0,0,0,1,0,0,0,0,1,-0.0004922987690640373,0,0,0,1],"contentsRect":{"y":0,"x":0,"width":1,"height":1},"opacity":1,"edgeAntialiasingMask":251658240,"height":306.9999933242798,"hidden":false,"anchorPoint":{"pointX":0.499999975355001,"pointY":-0.1903139941690736}},"layers":[{"animations":[{"timeOffset":0,"from":{"scalar":true},"beginTime":1e-100,"repeatCount":0,"fillMode":"both","property":"hidden","autoreverses":false,"duration":0.01,"to":{"scalar":false}}],"layers":[],"texturedRectangle":{"singleTextureOpacity":1,"textXHeight":0.4964210526315789,"textBaseline":0.7406986512635884,"isBackgroundTexture":false,"isVerticalText":false,"textColor":[0,0,0,1],"textureType":6},"initialState":{"affineTransform":[1,0,0,1,0,0],"masksToBounds":false,"rotation":0,"scale":1,"position":{"pointX":181.1787719726562,"pointY":157.5736050605774},"width":286,"sublayerTransform":[1,0,0,0,0,1,0,0,0,0,1,0,0,0,0,1],"contentsRect":{"y":0,"x":0,"width":1,"height":1},"opacity":1,"edgeAntialiasingMask":0,"height":38,"hidden":true,"anchorPoint":{"pointX":0.5,"pointY":0.5}},"texture":"4758254A91C6C40CDEF4C0480BD9C517"}]},{"animations":[],"layers":[],"texturedRectangle":{"singleTextureOpacity":1,"textXHeight":0.5548235294117646,"textBaseline":0.7101926102357752,"isBackgroundTexture":false,"isVerticalText":false,"textColor":[0,0,0,1],"textureType":6},"initialState":{"affineTransform":[1,0,0,1,0,0],"masksToBounds":false,"rotation":0,"scale":1,"position":{"pointX":101.1787719726562,"pointY":223.5736050605774},"width":126,"sublayerTransform":[1,0,0,0,0,1,0,0,0,0,1,0,0,0,0,1],"contentsRect":{"y":0,"x":0,"width":1,"height":1},"opacity":1,"edgeAntialiasingMask":0,"height":34,"hidden":true,"anchorPoint":{"pointX":0.5,"pointY":0.5}},"texture":"231BDE32EF29B8046E109B565B0FE118"},{"animations":[],"layers":[],"texturedRectangle":{"singleTextureOpacity":1,"textXHeight":0.5894999999999999,"textBaseline":0.8795796483755112,"isBackgroundTexture":false,"isVerticalText":false,"textColor":[0,0,0,1],"textureType":6},"initialState":{"affineTransform":[1,0,0,1,0,0],"masksToBounds":false,"rotation":0,"scale":1,"position":{"pointX":242.1787719726562,"pointY":282.5736050605774},"width":408,"sublayerTransform":[1,0,0,0,0,1,0,0,0,0,1,0,0,0,0,1],"contentsRect":{"y":0,"x":0,"width":1,"height":1},"opacity":1,"edgeAntialiasingMask":0,"height":32,"hidden":true,"anchorPoint":{"pointX":0.5,"pointY":0.5}},"texture":"7ABF9014F850E57025F9AD2D5D453401"}]},"effects":[],"duration":0.01,"type":"buildIn","name":"apple:appear","objectID":"ADA2DAAC-977A-43BE-A665-8069D27319AD"}],"automaticPlay":false,"hyperlinks":[],"accessibility":[{"text":"Property Access","targetRectangle":{"y":72,"x":216.36,"width":591.2800000000002,"height":96}},{"text":"TypeError","targetRectangle":{"y":446.4263949394226,"x":353.8212275505066,"width":154.332,"height":43}},{"text":"undefined","targetRectangle":{"y":489.4263949394226,"x":353.8212275505066,"width":162.072,"height":64}},{"text":" function load(obj) {","targetRectangle":{"y":191.9975843429565,"x":60.09092712402344,"width":869.4,"height":77}},{"text":"   return obj.x;","targetRectangle":{"y":268.9975843429565,"x":60.09092712402344,"width":662.4,"height":77}},{"text":" }","targetRectangle":{"y":345.9975843429565,"x":60.09092712402344,"width":82.80000000000001,"height":77}}],"baseLayer":{"animations":[],"initialState":{"affineTransform":[1,0,0,1,0,0],"masksToBounds":false,"rotation":0,"scale":1,"position":{"pointX":512,"pointY":384},"width":1024,"sublayerTransform":[1,0,0,0,0,1,0,0,0,0,1,0,0,0,0,1],"contentsRect":{"y":0,"x":0,"width":1,"height":1},"opacity":1,"edgeAntialiasingMask":251658240,"height":768,"hidden":false,"anchorPoint":{"pointX":0.5,"pointY":0.5}},"layers":[{"animations":[],"initialState":{"affineTransform":[1,0,0,1,0,0],"masksToBounds":false,"rotation":0,"scale":1,"position":{"pointX":512,"pointY":384},"width":1024,"sublayerTransform":[1,0,0,0,0,1,0,0,0,0,1,0,0,0,0,1],"contentsRect":{"y":0,"x":0,"width":1,"height":1},"opacity":1,"edgeAntialiasingMask":251658240,"height":768,"hidden":false,"anchorPoint":{"pointX":0.5,"pointY":0.5}},"layers":[{"animations":[],"initialState":{"affineTransform":[1,0,0,1,0,0],"masksToBounds":false,"rotation":0,"scale":1,"position":{"pointX":512,"pointY":384},"width":1024,"sublayerTransform":[1,0,0,0,0,1,0,0,0,0,1,0,0,0,0,1],"contentsRect":{"y":0,"x":0,"width":1,"height":1},"opacity":1,"edgeAntialiasingMask":251658240,"height":768,"hidden":false,"anchorPoint":{"pointX":0.5,"pointY":0.5}},"layers":[{"animations":[],"layers":[],"texturedRectangle":{"isBackgroundTexture":true,"singleTextureOpacity":1,"textureType":1,"textBaseline":0,"textXHeight":0,"isVerticalText":false},"initialState":{"affineTransform":[1,0,0,1,0,0],"masksToBounds":false,"rotation":0,"scale":1,"position":{"pointX":512,"pointY":384},"width":1024,"sublayerTransform":[1,0,0,0,0,1,0,0,0,0,1,0,0,0,0,1],"contentsRect":{"y":0,"x":0,"width":1,"height":1},"opacity":1,"edgeAntialiasingMask":0,"height":768,"hidden":false,"anchorPoint":{"pointX":0.5,"pointY":0.5}},"texture":"498E23C82CA78A4BCD7BA88E5243B6FC"}]}]},{"animations":[],"initialState":{"affineTransform":[1,0,0,1,0,0],"masksToBounds":false,"rotation":0,"scale":1,"position":{"pointX":512,"pointY":384},"width":1024,"sublayerTransform":[1,0,0,0,0,1,0,0,0,0,1,0,0,0,0,1],"contentsRect":{"y":0,"x":0,"width":1,"height":1},"opacity":1,"edgeAntialiasingMask":251658240,"height":768,"hidden":false,"anchorPoint":{"pointX":0.5,"pointY":0.5}},"layers":[{"animations":[],"initialState":{"affineTransform":[1,0,0,1,0,0],"masksToBounds":false,"rotation":0,"scale":1,"position":{"pointX":512,"pointY":120},"width":874,"sublayerTransform":[1,0,0,0,0,1,0,0,0,0,1,0,0,0,0,1],"contentsRect":{"y":0,"x":0,"width":1,"height":1},"opacity":1,"edgeAntialiasingMask":251658240,"height":170,"hidden":false,"anchorPoint":{"pointX":0.5,"pointY":0.5}},"objectID":"441ADC2F-0FBE-4955-BB1E-81EEA0F1C91D","layers":[{"animations":[],"layers":[],"texturedRectangle":{"singleTextureOpacity":1,"textXHeight":0.5515789473684211,"textBaseline":0.77105712890625,"isBackgroundTexture":true,"isVerticalText":false,"textColor":[0,0,0,1],"textureType":6},"initialState":{"affineTransform":[1,0,0,1,0,0],"masksToBounds":false,"rotation":0,"scale":1,"position":{"pointX":438,"pointY":94},"width":584,"sublayerTransform":[1,0,0,0,0,1,0,0,0,0,1,0,0,0,0,1],"contentsRect":{"y":0,"x":0,"width":1,"height":1},"opacity":1,"edgeAntialiasingMask":0,"height":76,"hidden":false,"anchorPoint":{"pointX":0.5,"pointY":0.5}},"texture":"75996AAD15AADBAD0B351AA53800C12A"}]}]},{"animations":[],"initialState":{"affineTransform":[1,0,0,1,0,0],"masksToBounds":false,"rotation":0,"scale":1,"position":{"pointX":512,"pointY":384},"width":1024,"sublayerTransform":[1,0,0,0,0,1,0,0,0,0,1,0,0,0,0,1],"contentsRect":{"y":0,"x":0,"width":1,"height":1},"opacity":1,"edgeAntialiasingMask":251658240,"height":768,"hidden":false,"anchorPoint":{"pointX":0.5,"pointY":0.5}},"layers":[{"animations":[],"initialState":{"affineTransform":[1,0,0,1,0,0],"masksToBounds":false,"rotation":0,"scale":1,"position":{"pointX":512.0000114440918,"pointY":595.9263916015625},"width":464.3575668334961,"sublayerTransform":[1,0,0,0,0,1,0,0,0,0,1,0,0,0,0,1],"contentsRect":{"y":0,"x":0,"width":1,"height":1},"opacity":1,"edgeAntialiasingMask":251658240,"height":306.9999933242798,"hidden":false,"anchorPoint":{"pointX":0.5,"pointY":0.5}},"objectID":"ADA2DAAC-977A-43BE-A665-8069D27319AD","layers":[{"animations":[],"layers":[],"texturedRectangle":{"singleTextureOpacity":1,"textXHeight":0.4964210526315789,"textBaseline":0.7406986512635884,"isBackgroundTexture":false,"isVerticalText":false,"textColor":[0,0,0,1],"textureType":6},"initialState":{"affineTransform":[1,0,0,1,0,0],"masksToBounds":false,"rotation":0,"scale":1,"position":{"pointX":133.6787719726562,"pointY":29.57360506057739},"width":191,"sublayerTransform":[1,0,0,0,0,1,0,0,0,0,1,0,0,0,0,1],"contentsRect":{"y":0,"x":0,"width":1,"height":1},"opacity":1,"edgeAntialiasingMask":0,"height":38,"hidden":false,"anchorPoint":{"pointX":0.5,"pointY":0.5}},"texture":"962E02FEABF206A1B6439CEC08333644"},{"animations":[],"layers":[],"texturedRectangle":{"singleTextureOpacity":1,"textXHeight":0.5894999999999999,"textBaseline":0.8795796483755112,"isBackgroundTexture":false,"isVerticalText":false,"textColor":[0,0,0,1],"textureType":6},"initialState":{"affineTransform":[1,0,0,1,0,0],"masksToBounds":false,"rotation":0,"scale":1,"position":{"pointX":136.6787719726562,"pointY":90.57360506057739},"width":197,"sublayerTransform":[1,0,0,0,0,1,0,0,0,0,1,0,0,0,0,1],"contentsRect":{"y":0,"x":0,"width":1,"height":1},"opacity":1,"edgeAntialiasingMask":0,"height":32,"hidden":false,"anchorPoint":{"pointX":0.5,"pointY":0.5}},"texture":"B4C91EE1E5B54B1652C89239E55F6478"},{"animations":[],"layers":[],"texturedRectangle":{"singleTextureOpacity":1,"textXHeight":0.4964210526315789,"textBaseline":0.7406986512635884,"isBackgroundTexture":false,"isVerticalText":false,"textColor":[0,0,0,1],"textureType":6},"initialState":{"affineTransform":[1,0,0,1,0,0],"masksToBounds":false,"rotation":0,"scale":1,"position":{"pointX":181.1787719726562,"pointY":157.5736050605774},"width":286,"sublayerTransform":[1,0,0,0,0,1,0,0,0,0,1,0,0,0,0,1],"contentsRect":{"y":0,"x":0,"width":1,"height":1},"opacity":1,"edgeAntialiasingMask":0,"height":38,"hidden":true,"anchorPoint":{"pointX":0.5,"pointY":0.5}},"texture":"4758254A91C6C40CDEF4C0480BD9C517"},{"animations":[],"layers":[],"texturedRectangle":{"singleTextureOpacity":1,"textXHeight":0.5548235294117646,"textBaseline":0.7101926102357752,"isBackgroundTexture":false,"isVerticalText":false,"textColor":[0,0,0,1],"textureType":6},"initialState":{"affineTransform":[1,0,0,1,0,0],"masksToBounds":false,"rotation":0,"scale":1,"position":{"pointX":101.1787719726562,"pointY":223.5736050605774},"width":126,"sublayerTransform":[1,0,0,0,0,1,0,0,0,0,1,0,0,0,0,1],"contentsRect":{"y":0,"x":0,"width":1,"height":1},"opacity":1,"edgeAntialiasingMask":0,"height":34,"hidden":true,"anchorPoint":{"pointX":0.5,"pointY":0.5}},"texture":"231BDE32EF29B8046E109B565B0FE118"},{"animations":[],"layers":[],"texturedRectangle":{"singleTextureOpacity":1,"textXHeight":0.5894999999999999,"textBaseline":0.8795796483755112,"isBackgroundTexture":false,"isVerticalText":false,"textColor":[0,0,0,1],"textureType":6},"initialState":{"affineTransform":[1,0,0,1,0,0],"masksToBounds":false,"rotation":0,"scale":1,"position":{"pointX":242.1787719726562,"pointY":282.5736050605774},"width":408,"sublayerTransform":[1,0,0,0,0,1,0,0,0,0,1,0,0,0,0,1],"contentsRect":{"y":0,"x":0,"width":1,"height":1},"opacity":1,"edgeAntialiasingMask":0,"height":32,"hidden":true,"anchorPoint":{"pointX":0.5,"pointY":0.5}},"texture":"7ABF9014F850E57025F9AD2D5D453401"}]}]},{"animations":[],"initialState":{"affineTransform":[1,0,0,1,0,0],"masksToBounds":false,"rotation":0,"scale":1,"position":{"pointX":512,"pointY":384},"width":1024,"sublayerTransform":[1,0,0,0,0,1,0,0,0,0,1,0,0,0,0,1],"contentsRect":{"y":0,"x":0,"width":1,"height":1},"opacity":1,"edgeAntialiasingMask":251658240,"height":768,"hidden":false,"anchorPoint":{"pointX":0.5,"pointY":0.5}},"layers":[{"animations":[],"initialState":{"affineTransform":[1,0,0,1,0,0],"masksToBounds":false,"rotation":0,"scale":1,"position":{"pointX":512,"pointY":307.4975891113281},"width":913.8181457519531,"sublayerTransform":[1,0,0,0,0,1,0,0,0,0,1,0,0,0,0,1],"contentsRect":{"y":0,"x":0,"width":1,"height":1},"opacity":1,"edgeAntialiasingMask":251658240,"height":241.0000095367432,"hidden":false,"anchorPoint":{"pointX":0.5,"pointY":0.5}},"objectID":"AFE8CA3E-FAF9-4767-B23E-13DFA2880110","layers":[{"animations":[],"layers":[],"texturedRectangle":{"singleTextureOpacity":1,"textXHeight":0,"shapePath":{"lineWidth":1,"flatness":0.6,"lineCapStyle":0,"elements":[{"type":"MoveToPoint","points":[[9.590927124023438,9.497584342956543]]},{"type":"AddLine","points":[[922.4090728759766,9.497584342956543]]},{"type":"AddLine","points":[[922.4090728759766,249.4975938796997]]},{"type":"AddLine","points":[[9.590927124023438,249.4975938796997]]},{"type":"CloseSubpath"},{"type":"MoveToPoint","points":[[9.590927124023438,9.497584342956543]]}],"windingRule":0,"lineJoinStyle":0,"miterLimit":10},"isBackgroundTexture":true,"textBaseline":0,"isVerticalText":false,"textureType":5},"initialState":{"affineTransform":[1,0,0,1,0,0],"masksToBounds":false,"rotation":0,"scale":1,"position":{"pointX":456.9090728759766,"pointY":120.5024156570435},"width":932,"sublayerTransform":[1,0,0,0,0,1,0,0,0,0,1,0,0,0,0,1],"contentsRect":{"y":0,"x":0,"width":1,"height":1},"opacity":1,"edgeAntialiasingMask":0,"height":259,"hidden":false,"anchorPoint":{"pointX":0.5,"pointY":0.5}},"texture":"3B5F094C1248F300D48710F408F34F8C"}]}]}]}},{"effects":[{"beginTime":0,"baseLayer":{"animations":[],"initialState":{"affineTransform":[1,0,0,1,0,0],"masksToBounds":false,"rotation":0,"scale":1,"position":{"pointX":512.0000114440918,"pointY":595.9263916015625},"width":464.3575668334961,"sublayerTransform":[1,0,0,0,0,1,0,0,0,0,1,0,0,0,0,1],"contentsRect":{"y":0,"x":0,"width":1,"height":1},"opacity":1,"edgeAntialiasingMask":251658240,"height":306.9999933242798,"hidden":false,"anchorPoint":{"pointX":0.5,"pointY":0.5}},"objectID":"ADA2DAAC-977A-43BE-A665-8069D27319AD","layers":[{"animations":[],"layers":[],"texturedRectangle":{"singleTextureOpacity":1,"textXHeight":0.4964210526315789,"textBaseline":0.7406986512635884,"isBackgroundTexture":false,"isVerticalText":false,"textColor":[0,0,0,1],"textureType":6},"initialState":{"affineTransform":[1,0,0,1,0,0],"masksToBounds":false,"rotation":0,"scale":1,"position":{"pointX":133.6787719726562,"pointY":29.57360506057739},"width":191,"sublayerTransform":[1,0,0,0,0,1,0,0,0,0,1,0,0,0,0,1],"contentsRect":{"y":0,"x":0,"width":1,"height":1},"opacity":1,"edgeAntialiasingMask":0,"height":38,"hidden":false,"anchorPoint":{"pointX":0.5,"pointY":0.5}},"texture":"962E02FEABF206A1B6439CEC08333644"},{"animations":[],"layers":[],"texturedRectangle":{"singleTextureOpacity":1,"textXHeight":0.5894999999999999,"textBaseline":0.8795796483755112,"isBackgroundTexture":false,"isVerticalText":false,"textColor":[0,0,0,1],"textureType":6},"initialState":{"affineTransform":[1,0,0,1,0,0],"masksToBounds":false,"rotation":0,"scale":1,"position":{"pointX":136.6787719726562,"pointY":90.57360506057739},"width":197,"sublayerTransform":[1,0,0,0,0,1,0,0,0,0,1,0,0,0,0,1],"contentsRect":{"y":0,"x":0,"width":1,"height":1},"opacity":1,"edgeAntialiasingMask":0,"height":32,"hidden":false,"anchorPoint":{"pointX":0.5,"pointY":0.5}},"texture":"B4C91EE1E5B54B1652C89239E55F6478"},{"animations":[],"layers":[],"texturedRectangle":{"singleTextureOpacity":1,"textXHeight":0.4964210526315789,"textBaseline":0.7406986512635884,"isBackgroundTexture":false,"isVerticalText":false,"textColor":[0,0,0,1],"textureType":6},"initialState":{"affineTransform":[1,0,0,1,0,0],"masksToBounds":false,"rotation":0,"scale":1,"position":{"pointX":181.1787719726562,"pointY":157.5736050605774},"width":286,"sublayerTransform":[1,0,0,0,0,1,0,0,0,0,1,0,0,0,0,1],"contentsRect":{"y":0,"x":0,"width":1,"height":1},"opacity":1,"edgeAntialiasingMask":0,"height":38,"hidden":false,"anchorPoint":{"pointX":0.5,"pointY":0.5}},"texture":"4758254A91C6C40CDEF4C0480BD9C517"},{"animations":[],"initialState":{"affineTransform":[1,0,0,1,0,0],"masksToBounds":false,"rotation":0,"scale":1,"position":{"pointX":232.1787719726562,"pointY":-58.42639493942261},"width":464.3575668334961,"sublayerTransform":[1,0,0,0,0,1,0,0,0,0,1,-0.0004922987690640373,0,0,0,1],"contentsRect":{"y":0,"x":0,"width":1,"height":1},"opacity":1,"edgeAntialiasingMask":251658240,"height":306.9999933242798,"hidden":false,"anchorPoint":{"pointX":0.499999975355001,"pointY":-0.1903139941690736}},"layers":[{"animations":[{"timeOffset":0,"from":{"scalar":true},"beginTime":1e-100,"repeatCount":0,"fillMode":"both","property":"hidden","autoreverses":false,"duration":0.01,"to":{"scalar":false}}],"layers":[],"texturedRectangle":{"singleTextureOpacity":1,"textXHeight":0.5548235294117646,"textBaseline":0.7101926102357752,"isBackgroundTexture":false,"isVerticalText":false,"textColor":[0,0,0,1],"textureType":6},"initialState":{"affineTransform":[1,0,0,1,0,0],"masksToBounds":false,"rotation":0,"scale":1,"position":{"pointX":101.1787719726562,"pointY":223.5736050605774},"width":126,"sublayerTransform":[1,0,0,0,0,1,0,0,0,0,1,0,0,0,0,1],"contentsRect":{"y":0,"x":0,"width":1,"height":1},"opacity":1,"edgeAntialiasingMask":0,"height":34,"hidden":true,"anchorPoint":{"pointX":0.5,"pointY":0.5}},"texture":"231BDE32EF29B8046E109B565B0FE118"}]},{"animations":[],"layers":[],"texturedRectangle":{"singleTextureOpacity":1,"textXHeight":0.5894999999999999,"textBaseline":0.8795796483755112,"isBackgroundTexture":false,"isVerticalText":false,"textColor":[0,0,0,1],"textureType":6},"initialState":{"affineTransform":[1,0,0,1,0,0],"masksToBounds":false,"rotation":0,"scale":1,"position":{"pointX":242.1787719726562,"pointY":282.5736050605774},"width":408,"sublayerTransform":[1,0,0,0,0,1,0,0,0,0,1,0,0,0,0,1],"contentsRect":{"y":0,"x":0,"width":1,"height":1},"opacity":1,"edgeAntialiasingMask":0,"height":32,"hidden":true,"anchorPoint":{"pointX":0.5,"pointY":0.5}},"texture":"7ABF9014F850E57025F9AD2D5D453401"}]},"effects":[],"duration":0.01,"type":"buildIn","name":"apple:appear","objectID":"ADA2DAAC-977A-43BE-A665-8069D27319AD"}],"automaticPlay":false,"hyperlinks":[],"accessibility":[{"text":"Property Access","targetRectangle":{"y":72,"x":216.36,"width":591.2800000000002,"height":96}},{"text":"TypeError","targetRectangle":{"y":446.4263949394226,"x":353.8212275505066,"width":154.332,"height":43}},{"text":"undefined","targetRectangle":{"y":489.4263949394226,"x":353.8212275505066,"width":162.072,"height":64}},{"text":"prototype chain","targetRectangle":{"y":553.4263949394226,"x":353.8212275505066,"width":251.4599999999999,"height":64}},{"text":" function load(obj) {","targetRectangle":{"y":191.9975843429565,"x":60.09092712402344,"width":869.4,"height":77}},{"text":"   return obj.x;","targetRectangle":{"y":268.9975843429565,"x":60.09092712402344,"width":662.4,"height":77}},{"text":" }","targetRectangle":{"y":345.9975843429565,"x":60.09092712402344,"width":82.80000000000001,"height":77}}],"baseLayer":{"animations":[],"initialState":{"affineTransform":[1,0,0,1,0,0],"masksToBounds":false,"rotation":0,"scale":1,"position":{"pointX":512,"pointY":384},"width":1024,"sublayerTransform":[1,0,0,0,0,1,0,0,0,0,1,0,0,0,0,1],"contentsRect":{"y":0,"x":0,"width":1,"height":1},"opacity":1,"edgeAntialiasingMask":251658240,"height":768,"hidden":false,"anchorPoint":{"pointX":0.5,"pointY":0.5}},"layers":[{"animations":[],"initialState":{"affineTransform":[1,0,0,1,0,0],"masksToBounds":false,"rotation":0,"scale":1,"position":{"pointX":512,"pointY":384},"width":1024,"sublayerTransform":[1,0,0,0,0,1,0,0,0,0,1,0,0,0,0,1],"contentsRect":{"y":0,"x":0,"width":1,"height":1},"opacity":1,"edgeAntialiasingMask":251658240,"height":768,"hidden":false,"anchorPoint":{"pointX":0.5,"pointY":0.5}},"layers":[{"animations":[],"initialState":{"affineTransform":[1,0,0,1,0,0],"masksToBounds":false,"rotation":0,"scale":1,"position":{"pointX":512,"pointY":384},"width":1024,"sublayerTransform":[1,0,0,0,0,1,0,0,0,0,1,0,0,0,0,1],"contentsRect":{"y":0,"x":0,"width":1,"height":1},"opacity":1,"edgeAntialiasingMask":251658240,"height":768,"hidden":false,"anchorPoint":{"pointX":0.5,"pointY":0.5}},"layers":[{"animations":[],"layers":[],"texturedRectangle":{"isBackgroundTexture":true,"singleTextureOpacity":1,"textureType":1,"textBaseline":0,"textXHeight":0,"isVerticalText":false},"initialState":{"affineTransform":[1,0,0,1,0,0],"masksToBounds":false,"rotation":0,"scale":1,"position":{"pointX":512,"pointY":384},"width":1024,"sublayerTransform":[1,0,0,0,0,1,0,0,0,0,1,0,0,0,0,1],"contentsRect":{"y":0,"x":0,"width":1,"height":1},"opacity":1,"edgeAntialiasingMask":0,"height":768,"hidden":false,"anchorPoint":{"pointX":0.5,"pointY":0.5}},"texture":"498E23C82CA78A4BCD7BA88E5243B6FC"}]}]},{"animations":[],"initialState":{"affineTransform":[1,0,0,1,0,0],"masksToBounds":false,"rotation":0,"scale":1,"position":{"pointX":512,"pointY":384},"width":1024,"sublayerTransform":[1,0,0,0,0,1,0,0,0,0,1,0,0,0,0,1],"contentsRect":{"y":0,"x":0,"width":1,"height":1},"opacity":1,"edgeAntialiasingMask":251658240,"height":768,"hidden":false,"anchorPoint":{"pointX":0.5,"pointY":0.5}},"layers":[{"animations":[],"initialState":{"affineTransform":[1,0,0,1,0,0],"masksToBounds":false,"rotation":0,"scale":1,"position":{"pointX":512,"pointY":120},"width":874,"sublayerTransform":[1,0,0,0,0,1,0,0,0,0,1,0,0,0,0,1],"contentsRect":{"y":0,"x":0,"width":1,"height":1},"opacity":1,"edgeAntialiasingMask":251658240,"height":170,"hidden":false,"anchorPoint":{"pointX":0.5,"pointY":0.5}},"objectID":"441ADC2F-0FBE-4955-BB1E-81EEA0F1C91D","layers":[{"animations":[],"layers":[],"texturedRectangle":{"singleTextureOpacity":1,"textXHeight":0.5515789473684211,"textBaseline":0.77105712890625,"isBackgroundTexture":true,"isVerticalText":false,"textColor":[0,0,0,1],"textureType":6},"initialState":{"affineTransform":[1,0,0,1,0,0],"masksToBounds":false,"rotation":0,"scale":1,"position":{"pointX":438,"pointY":94},"width":584,"sublayerTransform":[1,0,0,0,0,1,0,0,0,0,1,0,0,0,0,1],"contentsRect":{"y":0,"x":0,"width":1,"height":1},"opacity":1,"edgeAntialiasingMask":0,"height":76,"hidden":false,"anchorPoint":{"pointX":0.5,"pointY":0.5}},"texture":"75996AAD15AADBAD0B351AA53800C12A"}]}]},{"animations":[],"initialState":{"affineTransform":[1,0,0,1,0,0],"masksToBounds":false,"rotation":0,"scale":1,"position":{"pointX":512,"pointY":384},"width":1024,"sublayerTransform":[1,0,0,0,0,1,0,0,0,0,1,0,0,0,0,1],"contentsRect":{"y":0,"x":0,"width":1,"height":1},"opacity":1,"edgeAntialiasingMask":251658240,"height":768,"hidden":false,"anchorPoint":{"pointX":0.5,"pointY":0.5}},"layers":[{"animations":[],"initialState":{"affineTransform":[1,0,0,1,0,0],"masksToBounds":false,"rotation":0,"scale":1,"position":{"pointX":512.0000114440918,"pointY":595.9263916015625},"width":464.3575668334961,"sublayerTransform":[1,0,0,0,0,1,0,0,0,0,1,0,0,0,0,1],"contentsRect":{"y":0,"x":0,"width":1,"height":1},"opacity":1,"edgeAntialiasingMask":251658240,"height":306.9999933242798,"hidden":false,"anchorPoint":{"pointX":0.5,"pointY":0.5}},"objectID":"ADA2DAAC-977A-43BE-A665-8069D27319AD","layers":[{"animations":[],"layers":[],"texturedRectangle":{"singleTextureOpacity":1,"textXHeight":0.4964210526315789,"textBaseline":0.7406986512635884,"isBackgroundTexture":false,"isVerticalText":false,"textColor":[0,0,0,1],"textureType":6},"initialState":{"affineTransform":[1,0,0,1,0,0],"masksToBounds":false,"rotation":0,"scale":1,"position":{"pointX":133.6787719726562,"pointY":29.57360506057739},"width":191,"sublayerTransform":[1,0,0,0,0,1,0,0,0,0,1,0,0,0,0,1],"contentsRect":{"y":0,"x":0,"width":1,"height":1},"opacity":1,"edgeAntialiasingMask":0,"height":38,"hidden":false,"anchorPoint":{"pointX":0.5,"pointY":0.5}},"texture":"962E02FEABF206A1B6439CEC08333644"},{"animations":[],"layers":[],"texturedRectangle":{"singleTextureOpacity":1,"textXHeight":0.5894999999999999,"textBaseline":0.8795796483755112,"isBackgroundTexture":false,"isVerticalText":false,"textColor":[0,0,0,1],"textureType":6},"initialState":{"affineTransform":[1,0,0,1,0,0],"masksToBounds":false,"rotation":0,"scale":1,"position":{"pointX":136.6787719726562,"pointY":90.57360506057739},"width":197,"sublayerTransform":[1,0,0,0,0,1,0,0,0,0,1,0,0,0,0,1],"contentsRect":{"y":0,"x":0,"width":1,"height":1},"opacity":1,"edgeAntialiasingMask":0,"height":32,"hidden":false,"anchorPoint":{"pointX":0.5,"pointY":0.5}},"texture":"B4C91EE1E5B54B1652C89239E55F6478"},{"animations":[],"layers":[],"texturedRectangle":{"singleTextureOpacity":1,"textXHeight":0.4964210526315789,"textBaseline":0.7406986512635884,"isBackgroundTexture":false,"isVerticalText":false,"textColor":[0,0,0,1],"textureType":6},"initialState":{"affineTransform":[1,0,0,1,0,0],"masksToBounds":false,"rotation":0,"scale":1,"position":{"pointX":181.1787719726562,"pointY":157.5736050605774},"width":286,"sublayerTransform":[1,0,0,0,0,1,0,0,0,0,1,0,0,0,0,1],"contentsRect":{"y":0,"x":0,"width":1,"height":1},"opacity":1,"edgeAntialiasingMask":0,"height":38,"hidden":false,"anchorPoint":{"pointX":0.5,"pointY":0.5}},"texture":"4758254A91C6C40CDEF4C0480BD9C517"},{"animations":[],"layers":[],"texturedRectangle":{"singleTextureOpacity":1,"textXHeight":0.5548235294117646,"textBaseline":0.7101926102357752,"isBackgroundTexture":false,"isVerticalText":false,"textColor":[0,0,0,1],"textureType":6},"initialState":{"affineTransform":[1,0,0,1,0,0],"masksToBounds":false,"rotation":0,"scale":1,"position":{"pointX":101.1787719726562,"pointY":223.5736050605774},"width":126,"sublayerTransform":[1,0,0,0,0,1,0,0,0,0,1,0,0,0,0,1],"contentsRect":{"y":0,"x":0,"width":1,"height":1},"opacity":1,"edgeAntialiasingMask":0,"height":34,"hidden":true,"anchorPoint":{"pointX":0.5,"pointY":0.5}},"texture":"231BDE32EF29B8046E109B565B0FE118"},{"animations":[],"layers":[],"texturedRectangle":{"singleTextureOpacity":1,"textXHeight":0.5894999999999999,"textBaseline":0.8795796483755112,"isBackgroundTexture":false,"isVerticalText":false,"textColor":[0,0,0,1],"textureType":6},"initialState":{"affineTransform":[1,0,0,1,0,0],"masksToBounds":false,"rotation":0,"scale":1,"position":{"pointX":242.1787719726562,"pointY":282.5736050605774},"width":408,"sublayerTransform":[1,0,0,0,0,1,0,0,0,0,1,0,0,0,0,1],"contentsRect":{"y":0,"x":0,"width":1,"height":1},"opacity":1,"edgeAntialiasingMask":0,"height":32,"hidden":true,"anchorPoint":{"pointX":0.5,"pointY":0.5}},"texture":"7ABF9014F850E57025F9AD2D5D453401"}]}]},{"animations":[],"initialState":{"affineTransform":[1,0,0,1,0,0],"masksToBounds":false,"rotation":0,"scale":1,"position":{"pointX":512,"pointY":384},"width":1024,"sublayerTransform":[1,0,0,0,0,1,0,0,0,0,1,0,0,0,0,1],"contentsRect":{"y":0,"x":0,"width":1,"height":1},"opacity":1,"edgeAntialiasingMask":251658240,"height":768,"hidden":false,"anchorPoint":{"pointX":0.5,"pointY":0.5}},"layers":[{"animations":[],"initialState":{"affineTransform":[1,0,0,1,0,0],"masksToBounds":false,"rotation":0,"scale":1,"position":{"pointX":512,"pointY":307.4975891113281},"width":913.8181457519531,"sublayerTransform":[1,0,0,0,0,1,0,0,0,0,1,0,0,0,0,1],"contentsRect":{"y":0,"x":0,"width":1,"height":1},"opacity":1,"edgeAntialiasingMask":251658240,"height":241.0000095367432,"hidden":false,"anchorPoint":{"pointX":0.5,"pointY":0.5}},"objectID":"AFE8CA3E-FAF9-4767-B23E-13DFA2880110","layers":[{"animations":[],"layers":[],"texturedRectangle":{"singleTextureOpacity":1,"textXHeight":0,"shapePath":{"lineWidth":1,"flatness":0.6,"lineCapStyle":0,"elements":[{"type":"MoveToPoint","points":[[9.590927124023438,9.497584342956543]]},{"type":"AddLine","points":[[922.4090728759766,9.497584342956543]]},{"type":"AddLine","points":[[922.4090728759766,249.4975938796997]]},{"type":"AddLine","points":[[9.590927124023438,249.4975938796997]]},{"type":"CloseSubpath"},{"type":"MoveToPoint","points":[[9.590927124023438,9.497584342956543]]}],"windingRule":0,"lineJoinStyle":0,"miterLimit":10},"isBackgroundTexture":true,"textBaseline":0,"isVerticalText":false,"textureType":5},"initialState":{"affineTransform":[1,0,0,1,0,0],"masksToBounds":false,"rotation":0,"scale":1,"position":{"pointX":456.9090728759766,"pointY":120.5024156570435},"width":932,"sublayerTransform":[1,0,0,0,0,1,0,0,0,0,1,0,0,0,0,1],"contentsRect":{"y":0,"x":0,"width":1,"height":1},"opacity":1,"edgeAntialiasingMask":0,"height":259,"hidden":false,"anchorPoint":{"pointX":0.5,"pointY":0.5}},"texture":"3B5F094C1248F300D48710F408F34F8C"}]}]}]}},{"effects":[{"beginTime":0,"baseLayer":{"animations":[],"initialState":{"affineTransform":[1,0,0,1,0,0],"masksToBounds":false,"rotation":0,"scale":1,"position":{"pointX":512.0000114440918,"pointY":595.9263916015625},"width":464.3575668334961,"sublayerTransform":[1,0,0,0,0,1,0,0,0,0,1,0,0,0,0,1],"contentsRect":{"y":0,"x":0,"width":1,"height":1},"opacity":1,"edgeAntialiasingMask":251658240,"height":306.9999933242798,"hidden":false,"anchorPoint":{"pointX":0.5,"pointY":0.5}},"objectID":"ADA2DAAC-977A-43BE-A665-8069D27319AD","layers":[{"animations":[],"layers":[],"texturedRectangle":{"singleTextureOpacity":1,"textXHeight":0.4964210526315789,"textBaseline":0.7406986512635884,"isBackgroundTexture":false,"isVerticalText":false,"textColor":[0,0,0,1],"textureType":6},"initialState":{"affineTransform":[1,0,0,1,0,0],"masksToBounds":false,"rotation":0,"scale":1,"position":{"pointX":133.6787719726562,"pointY":29.57360506057739},"width":191,"sublayerTransform":[1,0,0,0,0,1,0,0,0,0,1,0,0,0,0,1],"contentsRect":{"y":0,"x":0,"width":1,"height":1},"opacity":1,"edgeAntialiasingMask":0,"height":38,"hidden":false,"anchorPoint":{"pointX":0.5,"pointY":0.5}},"texture":"962E02FEABF206A1B6439CEC08333644"},{"animations":[],"layers":[],"texturedRectangle":{"singleTextureOpacity":1,"textXHeight":0.5894999999999999,"textBaseline":0.8795796483755112,"isBackgroundTexture":false,"isVerticalText":false,"textColor":[0,0,0,1],"textureType":6},"initialState":{"affineTransform":[1,0,0,1,0,0],"masksToBounds":false,"rotation":0,"scale":1,"position":{"pointX":136.6787719726562,"pointY":90.57360506057739},"width":197,"sublayerTransform":[1,0,0,0,0,1,0,0,0,0,1,0,0,0,0,1],"contentsRect":{"y":0,"x":0,"width":1,"height":1},"opacity":1,"edgeAntialiasingMask":0,"height":32,"hidden":false,"anchorPoint":{"pointX":0.5,"pointY":0.5}},"texture":"B4C91EE1E5B54B1652C89239E55F6478"},{"animations":[],"layers":[],"texturedRectangle":{"singleTextureOpacity":1,"textXHeight":0.4964210526315789,"textBaseline":0.7406986512635884,"isBackgroundTexture":false,"isVerticalText":false,"textColor":[0,0,0,1],"textureType":6},"initialState":{"affineTransform":[1,0,0,1,0,0],"masksToBounds":false,"rotation":0,"scale":1,"position":{"pointX":181.1787719726562,"pointY":157.5736050605774},"width":286,"sublayerTransform":[1,0,0,0,0,1,0,0,0,0,1,0,0,0,0,1],"contentsRect":{"y":0,"x":0,"width":1,"height":1},"opacity":1,"edgeAntialiasingMask":0,"height":38,"hidden":false,"anchorPoint":{"pointX":0.5,"pointY":0.5}},"texture":"4758254A91C6C40CDEF4C0480BD9C517"},{"animations":[],"layers":[],"texturedRectangle":{"singleTextureOpacity":1,"textXHeight":0.5548235294117646,"textBaseline":0.7101926102357752,"isBackgroundTexture":false,"isVerticalText":false,"textColor":[0,0,0,1],"textureType":6},"initialState":{"affineTransform":[1,0,0,1,0,0],"masksToBounds":false,"rotation":0,"scale":1,"position":{"pointX":101.1787719726562,"pointY":223.5736050605774},"width":126,"sublayerTransform":[1,0,0,0,0,1,0,0,0,0,1,0,0,0,0,1],"contentsRect":{"y":0,"x":0,"width":1,"height":1},"opacity":1,"edgeAntialiasingMask":0,"height":34,"hidden":false,"anchorPoint":{"pointX":0.5,"pointY":0.5}},"texture":"231BDE32EF29B8046E109B565B0FE118"},{"animations":[],"initialState":{"affineTransform":[1,0,0,1,0,0],"masksToBounds":false,"rotation":0,"scale":1,"position":{"pointX":232.1787719726562,"pointY":-58.42639493942261},"width":464.3575668334961,"sublayerTransform":[1,0,0,0,0,1,0,0,0,0,1,-0.0004922987690640373,0,0,0,1],"contentsRect":{"y":0,"x":0,"width":1,"height":1},"opacity":1,"edgeAntialiasingMask":251658240,"height":306.9999933242798,"hidden":false,"anchorPoint":{"pointX":0.499999975355001,"pointY":-0.1903139941690736}},"layers":[{"animations":[{"timeOffset":0,"from":{"scalar":true},"beginTime":1e-100,"repeatCount":0,"fillMode":"both","property":"hidden","autoreverses":false,"duration":0.01,"to":{"scalar":false}}],"layers":[],"texturedRectangle":{"singleTextureOpacity":1,"textXHeight":0.5894999999999999,"textBaseline":0.8795796483755112,"isBackgroundTexture":false,"isVerticalText":false,"textColor":[0,0,0,1],"textureType":6},"initialState":{"affineTransform":[1,0,0,1,0,0],"masksToBounds":false,"rotation":0,"scale":1,"position":{"pointX":242.1787719726562,"pointY":282.5736050605774},"width":408,"sublayerTransform":[1,0,0,0,0,1,0,0,0,0,1,0,0,0,0,1],"contentsRect":{"y":0,"x":0,"width":1,"height":1},"opacity":1,"edgeAntialiasingMask":0,"height":32,"hidden":true,"anchorPoint":{"pointX":0.5,"pointY":0.5}},"texture":"7ABF9014F850E57025F9AD2D5D453401"}]}]},"effects":[],"duration":0.01,"type":"buildIn","name":"apple:appear","objectID":"ADA2DAAC-977A-43BE-A665-8069D27319AD"}],"automaticPlay":false,"hyperlinks":[],"accessibility":[{"text":"Property Access","targetRectangle":{"y":72,"x":216.36,"width":591.2800000000002,"height":96}},{"text":"TypeError","targetRectangle":{"y":446.4263949394226,"x":353.8212275505066,"width":154.332,"height":43}},{"text":"undefined","targetRectangle":{"y":489.4263949394226,"x":353.8212275505066,"width":162.072,"height":64}},{"text":"prototype chain","targetRectangle":{"y":553.4263949394226,"x":353.8212275505066,"width":251.4599999999999,"height":64}},{"text":"proxy","targetRectangle":{"y":617.4263949394226,"x":353.8212275505066,"width":89.35199999999998,"height":64}},{"text":" function load(obj) {","targetRectangle":{"y":191.9975843429565,"x":60.09092712402344,"width":869.4,"height":77}},{"text":"   return obj.x;","targetRectangle":{"y":268.9975843429565,"x":60.09092712402344,"width":662.4,"height":77}},{"text":" }","targetRectangle":{"y":345.9975843429565,"x":60.09092712402344,"width":82.80000000000001,"height":77}}],"baseLayer":{"animations":[],"initialState":{"affineTransform":[1,0,0,1,0,0],"masksToBounds":false,"rotation":0,"scale":1,"position":{"pointX":512,"pointY":384},"width":1024,"sublayerTransform":[1,0,0,0,0,1,0,0,0,0,1,0,0,0,0,1],"contentsRect":{"y":0,"x":0,"width":1,"height":1},"opacity":1,"edgeAntialiasingMask":251658240,"height":768,"hidden":false,"anchorPoint":{"pointX":0.5,"pointY":0.5}},"layers":[{"animations":[],"initialState":{"affineTransform":[1,0,0,1,0,0],"masksToBounds":false,"rotation":0,"scale":1,"position":{"pointX":512,"pointY":384},"width":1024,"sublayerTransform":[1,0,0,0,0,1,0,0,0,0,1,0,0,0,0,1],"contentsRect":{"y":0,"x":0,"width":1,"height":1},"opacity":1,"edgeAntialiasingMask":251658240,"height":768,"hidden":false,"anchorPoint":{"pointX":0.5,"pointY":0.5}},"layers":[{"animations":[],"initialState":{"affineTransform":[1,0,0,1,0,0],"masksToBounds":false,"rotation":0,"scale":1,"position":{"pointX":512,"pointY":384},"width":1024,"sublayerTransform":[1,0,0,0,0,1,0,0,0,0,1,0,0,0,0,1],"contentsRect":{"y":0,"x":0,"width":1,"height":1},"opacity":1,"edgeAntialiasingMask":251658240,"height":768,"hidden":false,"anchorPoint":{"pointX":0.5,"pointY":0.5}},"layers":[{"animations":[],"layers":[],"texturedRectangle":{"isBackgroundTexture":true,"singleTextureOpacity":1,"textureType":1,"textBaseline":0,"textXHeight":0,"isVerticalText":false},"initialState":{"affineTransform":[1,0,0,1,0,0],"masksToBounds":false,"rotation":0,"scale":1,"position":{"pointX":512,"pointY":384},"width":1024,"sublayerTransform":[1,0,0,0,0,1,0,0,0,0,1,0,0,0,0,1],"contentsRect":{"y":0,"x":0,"width":1,"height":1},"opacity":1,"edgeAntialiasingMask":0,"height":768,"hidden":false,"anchorPoint":{"pointX":0.5,"pointY":0.5}},"texture":"498E23C82CA78A4BCD7BA88E5243B6FC"}]}]},{"animations":[],"initialState":{"affineTransform":[1,0,0,1,0,0],"masksToBounds":false,"rotation":0,"scale":1,"position":{"pointX":512,"pointY":384},"width":1024,"sublayerTransform":[1,0,0,0,0,1,0,0,0,0,1,0,0,0,0,1],"contentsRect":{"y":0,"x":0,"width":1,"height":1},"opacity":1,"edgeAntialiasingMask":251658240,"height":768,"hidden":false,"anchorPoint":{"pointX":0.5,"pointY":0.5}},"layers":[{"animations":[],"initialState":{"affineTransform":[1,0,0,1,0,0],"masksToBounds":false,"rotation":0,"scale":1,"position":{"pointX":512,"pointY":120},"width":874,"sublayerTransform":[1,0,0,0,0,1,0,0,0,0,1,0,0,0,0,1],"contentsRect":{"y":0,"x":0,"width":1,"height":1},"opacity":1,"edgeAntialiasingMask":251658240,"height":170,"hidden":false,"anchorPoint":{"pointX":0.5,"pointY":0.5}},"objectID":"441ADC2F-0FBE-4955-BB1E-81EEA0F1C91D","layers":[{"animations":[],"layers":[],"texturedRectangle":{"singleTextureOpacity":1,"textXHeight":0.5515789473684211,"textBaseline":0.77105712890625,"isBackgroundTexture":true,"isVerticalText":false,"textColor":[0,0,0,1],"textureType":6},"initialState":{"affineTransform":[1,0,0,1,0,0],"masksToBounds":false,"rotation":0,"scale":1,"position":{"pointX":438,"pointY":94},"width":584,"sublayerTransform":[1,0,0,0,0,1,0,0,0,0,1,0,0,0,0,1],"contentsRect":{"y":0,"x":0,"width":1,"height":1},"opacity":1,"edgeAntialiasingMask":0,"height":76,"hidden":false,"anchorPoint":{"pointX":0.5,"pointY":0.5}},"texture":"75996AAD15AADBAD0B351AA53800C12A"}]}]},{"animations":[],"initialState":{"affineTransform":[1,0,0,1,0,0],"masksToBounds":false,"rotation":0,"scale":1,"position":{"pointX":512,"pointY":384},"width":1024,"sublayerTransform":[1,0,0,0,0,1,0,0,0,0,1,0,0,0,0,1],"contentsRect":{"y":0,"x":0,"width":1,"height":1},"opacity":1,"edgeAntialiasingMask":251658240,"height":768,"hidden":false,"anchorPoint":{"pointX":0.5,"pointY":0.5}},"layers":[{"animations":[],"initialState":{"affineTransform":[1,0,0,1,0,0],"masksToBounds":false,"rotation":0,"scale":1,"position":{"pointX":512.0000114440918,"pointY":595.9263916015625},"width":464.3575668334961,"sublayerTransform":[1,0,0,0,0,1,0,0,0,0,1,0,0,0,0,1],"contentsRect":{"y":0,"x":0,"width":1,"height":1},"opacity":1,"edgeAntialiasingMask":251658240,"height":306.9999933242798,"hidden":false,"anchorPoint":{"pointX":0.5,"pointY":0.5}},"objectID":"ADA2DAAC-977A-43BE-A665-8069D27319AD","layers":[{"animations":[],"layers":[],"texturedRectangle":{"singleTextureOpacity":1,"textXHeight":0.4964210526315789,"textBaseline":0.7406986512635884,"isBackgroundTexture":false,"isVerticalText":false,"textColor":[0,0,0,1],"textureType":6},"initialState":{"affineTransform":[1,0,0,1,0,0],"masksToBounds":false,"rotation":0,"scale":1,"position":{"pointX":133.6787719726562,"pointY":29.57360506057739},"width":191,"sublayerTransform":[1,0,0,0,0,1,0,0,0,0,1,0,0,0,0,1],"contentsRect":{"y":0,"x":0,"width":1,"height":1},"opacity":1,"edgeAntialiasingMask":0,"height":38,"hidden":false,"anchorPoint":{"pointX":0.5,"pointY":0.5}},"texture":"962E02FEABF206A1B6439CEC08333644"},{"animations":[],"layers":[],"texturedRectangle":{"singleTextureOpacity":1,"textXHeight":0.5894999999999999,"textBaseline":0.8795796483755112,"isBackgroundTexture":false,"isVerticalText":false,"textColor":[0,0,0,1],"textureType":6},"initialState":{"affineTransform":[1,0,0,1,0,0],"masksToBounds":false,"rotation":0,"scale":1,"position":{"pointX":136.6787719726562,"pointY":90.57360506057739},"width":197,"sublayerTransform":[1,0,0,0,0,1,0,0,0,0,1,0,0,0,0,1],"contentsRect":{"y":0,"x":0,"width":1,"height":1},"opacity":1,"edgeAntialiasingMask":0,"height":32,"hidden":false,"anchorPoint":{"pointX":0.5,"pointY":0.5}},"texture":"B4C91EE1E5B54B1652C89239E55F6478"},{"animations":[],"layers":[],"texturedRectangle":{"singleTextureOpacity":1,"textXHeight":0.4964210526315789,"textBaseline":0.7406986512635884,"isBackgroundTexture":false,"isVerticalText":false,"textColor":[0,0,0,1],"textureType":6},"initialState":{"affineTransform":[1,0,0,1,0,0],"masksToBounds":false,"rotation":0,"scale":1,"position":{"pointX":181.1787719726562,"pointY":157.5736050605774},"width":286,"sublayerTransform":[1,0,0,0,0,1,0,0,0,0,1,0,0,0,0,1],"contentsRect":{"y":0,"x":0,"width":1,"height":1},"opacity":1,"edgeAntialiasingMask":0,"height":38,"hidden":false,"anchorPoint":{"pointX":0.5,"pointY":0.5}},"texture":"4758254A91C6C40CDEF4C0480BD9C517"},{"animations":[],"layers":[],"texturedRectangle":{"singleTextureOpacity":1,"textXHeight":0.5548235294117646,"textBaseline":0.7101926102357752,"isBackgroundTexture":false,"isVerticalText":false,"textColor":[0,0,0,1],"textureType":6},"initialState":{"affineTransform":[1,0,0,1,0,0],"masksToBounds":false,"rotation":0,"scale":1,"position":{"pointX":101.1787719726562,"pointY":223.5736050605774},"width":126,"sublayerTransform":[1,0,0,0,0,1,0,0,0,0,1,0,0,0,0,1],"contentsRect":{"y":0,"x":0,"width":1,"height":1},"opacity":1,"edgeAntialiasingMask":0,"height":34,"hidden":false,"anchorPoint":{"pointX":0.5,"pointY":0.5}},"texture":"231BDE32EF29B8046E109B565B0FE118"},{"animations":[],"layers":[],"texturedRectangle":{"singleTextureOpacity":1,"textXHeight":0.5894999999999999,"textBaseline":0.8795796483755112,"isBackgroundTexture":false,"isVerticalText":false,"textColor":[0,0,0,1],"textureType":6},"initialState":{"affineTransform":[1,0,0,1,0,0],"masksToBounds":false,"rotation":0,"scale":1,"position":{"pointX":242.1787719726562,"pointY":282.5736050605774},"width":408,"sublayerTransform":[1,0,0,0,0,1,0,0,0,0,1,0,0,0,0,1],"contentsRect":{"y":0,"x":0,"width":1,"height":1},"opacity":1,"edgeAntialiasingMask":0,"height":32,"hidden":true,"anchorPoint":{"pointX":0.5,"pointY":0.5}},"texture":"7ABF9014F850E57025F9AD2D5D453401"}]}]},{"animations":[],"initialState":{"affineTransform":[1,0,0,1,0,0],"masksToBounds":false,"rotation":0,"scale":1,"position":{"pointX":512,"pointY":384},"width":1024,"sublayerTransform":[1,0,0,0,0,1,0,0,0,0,1,0,0,0,0,1],"contentsRect":{"y":0,"x":0,"width":1,"height":1},"opacity":1,"edgeAntialiasingMask":251658240,"height":768,"hidden":false,"anchorPoint":{"pointX":0.5,"pointY":0.5}},"layers":[{"animations":[],"initialState":{"affineTransform":[1,0,0,1,0,0],"masksToBounds":false,"rotation":0,"scale":1,"position":{"pointX":512,"pointY":307.4975891113281},"width":913.8181457519531,"sublayerTransform":[1,0,0,0,0,1,0,0,0,0,1,0,0,0,0,1],"contentsRect":{"y":0,"x":0,"width":1,"height":1},"opacity":1,"edgeAntialiasingMask":251658240,"height":241.0000095367432,"hidden":false,"anchorPoint":{"pointX":0.5,"pointY":0.5}},"objectID":"AFE8CA3E-FAF9-4767-B23E-13DFA2880110","layers":[{"animations":[],"layers":[],"texturedRectangle":{"singleTextureOpacity":1,"textXHeight":0,"shapePath":{"lineWidth":1,"flatness":0.6,"lineCapStyle":0,"elements":[{"type":"MoveToPoint","points":[[9.590927124023438,9.497584342956543]]},{"type":"AddLine","points":[[922.4090728759766,9.497584342956543]]},{"type":"AddLine","points":[[922.4090728759766,249.4975938796997]]},{"type":"AddLine","points":[[9.590927124023438,249.4975938796997]]},{"type":"CloseSubpath"},{"type":"MoveToPoint","points":[[9.590927124023438,9.497584342956543]]}],"windingRule":0,"lineJoinStyle":0,"miterLimit":10},"isBackgroundTexture":true,"textBaseline":0,"isVerticalText":false,"textureType":5},"initialState":{"affineTransform":[1,0,0,1,0,0],"masksToBounds":false,"rotation":0,"scale":1,"position":{"pointX":456.9090728759766,"pointY":120.5024156570435},"width":932,"sublayerTransform":[1,0,0,0,0,1,0,0,0,0,1,0,0,0,0,1],"contentsRect":{"y":0,"x":0,"width":1,"height":1},"opacity":1,"edgeAntialiasingMask":0,"height":259,"hidden":false,"anchorPoint":{"pointX":0.5,"pointY":0.5}},"texture":"3B5F094C1248F300D48710F408F34F8C"}]}]}]}},{"effects":[{"beginTime":0,"baseLayer":{"animations":[],"initialState":{"affineTransform":[1,0,0,1,0,0],"masksToBounds":false,"rotation":0,"scale":1,"position":{"pointX":512,"pointY":384},"width":1024,"sublayerTransform":[1,0,0,0,0,1,0,0,0,0,1,0,0,0,0,1],"contentsRect":{"y":0,"x":0,"width":1,"height":1},"opacity":1,"edgeAntialiasingMask":251658240,"height":768,"hidden":false,"anchorPoint":{"pointX":0.5,"pointY":0.5}},"objectID":"0","layers":[{"animations":[],"initialState":{"affineTransform":[1,0,0,1,0,0],"masksToBounds":false,"rotation":0,"scale":1,"position":{"pointX":512,"pointY":384},"width":1024,"sublayerTransform":[1,0,0,0,0,1,0,0,0,0,1,-0.0004922987690640373,0,0,0,1],"contentsRect":{"y":0,"x":0,"width":1,"height":1},"opacity":1,"edgeAntialiasingMask":251658240,"height":768,"hidden":false,"anchorPoint":{"pointX":0.5,"pointY":0.5}},"layers":[{"animations":[],"layers":[],"texturedRectangle":{"isBackgroundTexture":false,"singleTextureOpacity":1,"textureType":0,"textBaseline":0,"textXHeight":0,"isVerticalText":false},"initialState":{"affineTransform":[1,0,0,1,0,0],"masksToBounds":false,"rotation":0,"scale":1,"position":{"pointX":512,"pointY":384},"width":1024,"sublayerTransform":[1,0,0,0,0,1,0,0,0,0,1,0,0,0,0,1],"contentsRect":{"y":0,"x":0,"width":1,"height":1},"opacity":1,"edgeAntialiasingMask":0,"height":768,"hidden":false,"anchorPoint":{"pointX":0.5,"pointY":0.5}},"texture":"149C513879A790C36DF1D69D3EE61D09"},{"animations":[{"timeOffset":0,"from":{"scalar":false},"beginTime":0,"repeatCount":0,"fillMode":"both","property":"hidden","autoreverses":false,"duration":0.01,"to":{"scalar":true}}],"layers":[],"texturedRectangle":{"isBackgroundTexture":false,"singleTextureOpacity":1,"textureType":0,"textBaseline":0,"textXHeight":0,"isVerticalText":false},"initialState":{"affineTransform":[1,0,0,1,0,0],"masksToBounds":false,"rotation":0,"scale":1,"position":{"pointX":512,"pointY":384},"width":1024,"sublayerTransform":[1,0,0,0,0,1,0,0,0,0,1,0,0,0,0,1],"contentsRect":{"y":0,"x":0,"width":1,"height":1},"opacity":1,"edgeAntialiasingMask":0,"height":768,"hidden":false,"anchorPoint":{"pointX":0.5,"pointY":0.5}},"texture":"9524C4C86A6D666694F5B7B992FC70D1"}]}]},"effects":[],"duration":0.01,"type":"transition","name":"none","objectID":"0"}],"automaticPlay":false,"hyperlinks":[],"accessibility":[{"text":"Property Access","targetRectangle":{"y":72,"x":216.36,"width":591.2800000000002,"height":96}},{"text":"TypeError","targetRectangle":{"y":446.4263949394226,"x":353.8212275505066,"width":154.332,"height":43}},{"text":"undefined","targetRectangle":{"y":489.4263949394226,"x":353.8212275505066,"width":162.072,"height":64}},{"text":"prototype chain","targetRectangle":{"y":553.4263949394226,"x":353.8212275505066,"width":251.4599999999999,"height":64}},{"text":"proxy","targetRectangle":{"y":617.4263949394226,"x":353.8212275505066,"width":89.35199999999998,"height":64}},{"text":"side effects if accessor","targetRectangle":{"y":681.4263949394226,"x":353.8212275505066,"width":371.52,"height":64}},{"text":" function load(obj) {","targetRectangle":{"y":191.9975843429565,"x":60.09092712402344,"width":869.4,"height":77}},{"text":"   return obj.x;","targetRectangle":{"y":268.9975843429565,"x":60.09092712402344,"width":662.4,"height":77}},{"text":" }","targetRectangle":{"y":345.9975843429565,"x":60.09092712402344,"width":82.80000000000001,"height":77}}],"baseLayer":{"animations":[],"initialState":{"affineTransform":[1,0,0,1,0,0],"masksToBounds":false,"rotation":0,"scale":1,"position":{"pointX":512,"pointY":384},"width":1024,"sublayerTransform":[1,0,0,0,0,1,0,0,0,0,1,0,0,0,0,1],"contentsRect":{"y":0,"x":0,"width":1,"height":1},"opacity":1,"edgeAntialiasingMask":251658240,"height":768,"hidden":false,"anchorPoint":{"pointX":0.5,"pointY":0.5}},"objectID":"0","layers":[{"animations":[],"initialState":{"affineTransform":[1,0,0,1,0,0],"masksToBounds":false,"rotation":0,"scale":1,"position":{"pointX":512,"pointY":384},"width":1024,"sublayerTransform":[1,0,0,0,0,1,0,0,0,0,1,-0.0004922987690640373,0,0,0,1],"contentsRect":{"y":0,"x":0,"width":1,"height":1},"opacity":1,"edgeAntialiasingMask":251658240,"height":768,"hidden":false,"anchorPoint":{"pointX":0.5,"pointY":0.5}},"layers":[{"animations":[],"layers":[],"texturedRectangle":{"isBackgroundTexture":false,"singleTextureOpacity":1,"textureType":0,"textBaseline":0,"textXHeight":0,"isVerticalText":false},"initialState":{"affineTransform":[1,0,0,1,0,0],"masksToBounds":false,"rotation":0,"scale":1,"position":{"pointX":512,"pointY":384},"width":1024,"sublayerTransform":[1,0,0,0,0,1,0,0,0,0,1,0,0,0,0,1],"contentsRect":{"y":0,"x":0,"width":1,"height":1},"opacity":1,"edgeAntialiasingMask":0,"height":768,"hidden":false,"anchorPoint":{"pointX":0.5,"pointY":0.5}},"texture":"9524C4C86A6D666694F5B7B992FC70D1"}]}]}}]}